import java.io.BufferedReader;
import java.io.DataOutputStream;
import java.io.InputStreamReader;
import java.io.PrintStream;
import java.net.ConnectException;
import java.net.DatagramSocket;
import java.net.InetAddress;
import java.net.Socket;
import java.util.Random;
import java.util.Scanner;
import java.util.Timer;

public class a
{
  public static int a;
  public static int b;
  public static int c;
  public static int d;
  public static int e;
  public static int f;
  public static int g;
  public static int h;
  public static int i;
  public static int j;
  public static final int k = 30000;
  public static final int l = 1000;
  public static final int m = 4;
  public static final int n = 1000;
  public static final String o;
  public static boolean p;
  private static final String[] q;
  private static final String[] r;
  
  public static void main(String[] paramArrayOfString)
    throws Exception
  {
    a = Integer.parseInt(paramArrayOfString[0]);
    boolean bool = c.b;
    b = Integer.parseInt(paramArrayOfString[1]);
    c = Integer.parseInt(paramArrayOfString[2]);
    InetAddress localInetAddress = InetAddress.getByName(a(9936, 58043));
    f = new Random().nextInt(65536);
    g = h = f;
    i = j = 0;
    DatagramSocket localDatagramSocket = new DatagramSocket(50000 + a);
    d locald = new d(localDatagramSocket);
    Timer localTimer = new Timer();
    localTimer.schedule(locald, 1000L, 30000L);
    c localc = new c(localDatagramSocket);
    localc.start();
    b localb = new b();
    localb.start();
    Scanner localScanner = new Scanner(System.in);
    do
    {
      String str1;
      do
      {
        Object localObject2;
        Object localObject3;
        String str2;
        do
        {
          if ((str1 = localScanner.nextLine()).isEmpty()) {
            return;
          }
          if (!str1.equalsIgnoreCase(a(9943, 55141))) {
            break;
          }
          localObject1 = new Socket(localInetAddress, 50000 + b);
          localObject2 = new Socket(localInetAddress, 50000 + c);
          localObject3 = new DataOutputStream(((Socket)localObject1).getOutputStream());
          DataOutputStream localDataOutputStream1 = new DataOutputStream(((Socket)localObject2).getOutputStream());
          str2 = a(9951, 42350) + d + " " + e + " " + a;
          ((DataOutputStream)localObject3).writeBytes(str2 + "\n");
          localDataOutputStream1.writeBytes(str2 + "\n");
          BufferedReader localBufferedReader1 = new BufferedReader(new InputStreamReader(((Socket)localObject1).getInputStream()));
          BufferedReader localBufferedReader2 = new BufferedReader(new InputStreamReader(((Socket)localObject2).getInputStream()));
          localBufferedReader1.readLine();
          localBufferedReader2.readLine();
          ((Socket)localObject1).close();
          ((Socket)localObject2).close();
          Socket localSocket1 = new Socket(localInetAddress, 50000 + d);
          DataOutputStream localDataOutputStream3 = new DataOutputStream(localSocket1.getOutputStream());
          str2 = a(9942, 5585) + b + " " + c + " " + a;
          localDataOutputStream3.writeBytes(str2 + "\n");
          BufferedReader localBufferedReader3 = new BufferedReader(new InputStreamReader(localSocket1.getInputStream()));
          localBufferedReader3.readLine();
          localSocket1.close();
          if (e != c)
          {
            Socket localSocket2 = new Socket(localInetAddress, 50000 + e);
            DataOutputStream localDataOutputStream4 = new DataOutputStream(localSocket2.getOutputStream());
            localDataOutputStream4.writeBytes(str2 + "\n");
            BufferedReader localBufferedReader4 = new BufferedReader(new InputStreamReader(localSocket2.getInputStream()));
            localBufferedReader4.readLine();
            localSocket2.close();
          }
          System.out.println(a(9937, 9850) + a + a(9941, 7606));
          System.exit(0);
        } while (!bool);
        try
        {
          if (p) {
            tmpTernaryOp = false;
          }
        }
        catch (ConnectException localConnectException2)
        {
          throw localConnectException2;
        }
        p = true;
        try
        {
          if ((str1.length() != 12) || (!str1.substring(0, 7).equalsIgnoreCase(a(9948, 60910)))) {
            break;
          }
        }
        catch (ConnectException localConnectException3)
        {
          throw localConnectException3;
        }
        Object localObject1 = str1.substring(8, str1.length());
        try
        {
          localObject2 = Integer.valueOf(Integer.parseInt((String)localObject1) % 256);
          try
          {
            localObject3 = new Socket(localInetAddress, 50000 + b);
          }
          catch (ConnectException localConnectException1)
          {
            localObject3 = new Socket(localInetAddress, 50000 + c);
          }
          DataOutputStream localDataOutputStream2 = new DataOutputStream(((Socket)localObject3).getOutputStream());
          str2 = a(9938, 7645) + (String)localObject1 + " " + a + " " + a;
          localDataOutputStream2.writeBytes(str2 + "\n");
          ((Socket)localObject3).close();
          System.out.println(a(9950, 12331) + (String)localObject1 + a(9949, 49102) + localObject2 + ".");
        }
        catch (NumberFormatException localNumberFormatException)
        {
          System.out.println(a(9940, 54771));
        }
      } while (!bool);
      System.out.println(a(9944, 10736) + str1);
      System.out.println(a(9945, 30794));
    } while (!bool);
  }
  
  /* Error */
  private static String a(int arg0, int arg1)
  {
    // Byte code:
    //   0: iload_0
    //   1: sipush 9941
    //   4: ixor
    //   5: ldc 6
    //   7: iand
    //   8: istore_2
    //   9: getstatic 248	a:r	[Ljava/lang/String;
    //   12: iload_2
    //   13: aaload
    //   14: ifnonnull +2600 -> 2614
    //   17: getstatic 236	a:q	[Ljava/lang/String;
    //   20: iload_2
    //   21: aaload
    //   22: invokevirtual 243	java/lang/String:toCharArray	()[C
    //   25: astore_3
    //   26: aload_3
    //   27: iconst_0
    //   28: caload
    //   29: sipush 255
    //   32: iand
    //   33: tableswitch	default:+2432->2465, 0:+1035->1068, 1:+1041->1074, 2:+1047->1080, 3:+1052->1085, 4:+1057->1090, 5:+1062->1095, 6:+1067->1100, 7:+1073->1106, 8:+1079->1112, 9:+1085->1118, 10:+1091->1124, 11:+1096->1129, 12:+1101->1134, 13:+1107->1140, 14:+1112->1145, 15:+1118->1151, 16:+1123->1156, 17:+1129->1162, 18:+1135->1168, 19:+1141->1174, 20:+1147->1180, 21:+1153->1186, 22:+1159->1192, 23:+1165->1198, 24:+1170->1203, 25:+1176->1209, 26:+1181->1214, 27:+1185->1218, 28:+1191->1224, 29:+1197->1230, 30:+1203->1236, 31:+1208->1241, 32:+1214->1247, 33:+1219->1252, 34:+1225->1258, 35:+1231->1264, 36:+1237->1270, 37:+1242->1275, 38:+1248->1281, 39:+1253->1286, 40:+1258->1291, 41:+1264->1297, 42:+1269->1302, 43:+1275->1308, 44:+1280->1313, 45:+1286->1319, 46:+1292->1325, 47:+1297->1330, 48:+1302->1335, 49:+1308->1341, 50:+1313->1346, 51:+1319->1352, 52:+1324->1357, 53:+1330->1363, 54:+1336->1369, 55:+1341->1374, 56:+1346->1379, 57:+1351->1384, 58:+1357->1390, 59:+1362->1395, 60:+1367->1400, 61:+1373->1406, 62:+1379->1412, 63:+1384->1417, 64:+1389->1422, 65:+1394->1427, 66:+1400->1433, 67:+1406->1439, 68:+1411->1444, 69:+1416->1449, 70:+1422->1455, 71:+1427->1460, 72:+1432->1465, 73:+1438->1471, 74:+1444->1477, 75:+1450->1483, 76:+1456->1489, 77:+1461->1494, 78:+1467->1500, 79:+1472->1505, 80:+1477->1510, 81:+1482->1515, 82:+1488->1521, 83:+1493->1526, 84:+1498->1531, 85:+1504->1537, 86:+1510->1543, 87:+1515->1548, 88:+1521->1554, 89:+1526->1559, 90:+1532->1565, 91:+1538->1571, 92:+1544->1577, 93:+1549->1582, 94:+1554->1587, 95:+1559->1592, 96:+1564->1597, 97:+1569->1602, 98:+1574->1607, 99:+1579->1612, 100:+1585->1618, 101:+1590->1623, 102:+1596->1629, 103:+1601->1634, 104:+1606->1639, 105:+1611->1644, 106:+1617->1650, 107:+1622->1655, 108:+1628->1661, 109:+1633->1666, 110:+1639->1672, 111:+1644->1677, 112:+1650->1683, 113:+1655->1688, 114:+1660->1693, 115:+1665->1698, 116:+1670->1703, 117:+1675->1708, 118:+1679->1712, 119:+1685->1718, 120:+1691->1724, 121:+1696->1729, 122:+1702->1735, 123:+1707->1740, 124:+1713->1746, 125:+1718->1751, 126:+1723->1756, 127:+1728->1761, 128:+1734->1767, 129:+1739->1772, 130:+1745->1778, 131:+1751->1784, 132:+1757->1790, 133:+1763->1796, 134:+1768->1801, 135:+1773->1806, 136:+1778->1811, 137:+1783->1816, 138:+1788->1821, 139:+1793->1826, 140:+1799->1832, 141:+1804->1837, 142:+1809->1842, 143:+1815->1848, 144:+1821->1854, 145:+1826->1859, 146:+1831->1864, 147:+1836->1869, 148:+1841->1874, 149:+1846->1879, 150:+1852->1885, 151:+1857->1890, 152:+1862->1895, 153:+1868->1901, 154:+1873->1906, 155:+1878->1911, 156:+1884->1917, 157:+1890->1923, 158:+1896->1929, 159:+1902->1935, 160:+1906->1939, 161:+1911->1944, 162:+1917->1950, 163:+1923->1956, 164:+1928->1961, 165:+1934->1967, 166:+1940->1973, 167:+1946->1979, 168:+1952->1985, 169:+1957->1990, 170:+1963->1996, 171:+1968->2001, 172:+1974->2007, 173:+1980->2013, 174:+1986->2019, 175:+1991->2024, 176:+1997->2030, 177:+2002->2035, 178:+2007->2040, 179:+2012->2045, 180:+2017->2050, 181:+2023->2056, 182:+2028->2061, 183:+2034->2067, 184:+2040->2073, 185:+2045->2078, 186:+2051->2084, 187:+2057->2090, 188:+2063->2096, 189:+2069->2102, 190:+2075->2108, 191:+2080->2113, 192:+2086->2119, 193:+2091->2124, 194:+2097->2130, 195:+2103->2136, 196:+2108->2141, 197:+2113->2146, 198:+2119->2152, 199:+2125->2158, 200:+2130->2163, 201:+2135->2168, 202:+2140->2173, 203:+2145->2178, 204:+2151->2184, 205:+2155->2188, 206:+2161->2194, 207:+2167->2200, 208:+2172->2205, 209:+2178->2211, 210:+2183->2216, 211:+2188->2221, 212:+2193->2226, 213:+2198->2231, 214:+2202->2235, 215:+2208->2241, 216:+2213->2246, 217:+2218->2251, 218:+2224->2257, 219:+2229->2262, 220:+2234->2267, 221:+2240->2273, 222:+2246->2279, 223:+2252->2285, 224:+2258->2291, 225:+2263->2296, 226:+2269->2302, 227:+2274->2307, 228:+2280->2313, 229:+2286->2319, 230:+2291->2324, 231:+2296->2329, 232:+2302->2335, 233:+2307->2340, 234:+2313->2346, 235:+2318->2351, 236:+2324->2357, 237:+2330->2363, 238:+2334->2367, 239:+2340->2373, 240:+2345->2378, 241:+2351->2384, 242:+2357->2390, 243:+2363->2396, 244:+2368->2401, 245:+2374->2407, 246:+2380->2413, 247:+2385->2418, 248:+2391->2424, 249:+2397->2430, 250:+2403->2436, 251:+2409->2442, 252:+2414->2447, 253:+2420->2453, 254:+2426->2459
    //   1068: sipush 196
    //   1071: goto +1396 -> 2467
    //   1074: sipush 186
    //   1077: goto +1390 -> 2467
    //   1080: bipush 79
    //   1082: goto +1385 -> 2467
    //   1085: bipush 49
    //   1087: goto +1380 -> 2467
    //   1090: bipush 107
    //   1092: goto +1375 -> 2467
    //   1095: bipush 81
    //   1097: goto +1370 -> 2467
    //   1100: sipush 179
    //   1103: goto +1364 -> 2467
    //   1106: sipush 222
    //   1109: goto +1358 -> 2467
    //   1112: sipush 236
    //   1115: goto +1352 -> 2467
    //   1118: sipush 211
    //   1121: goto +1346 -> 2467
    //   1124: bipush 62
    //   1126: goto +1341 -> 2467
    //   1129: bipush 91
    //   1131: goto +1336 -> 2467
    //   1134: sipush 170
    //   1137: goto +1330 -> 2467
    //   1140: bipush 41
    //   1142: goto +1325 -> 2467
    //   1145: sipush 190
    //   1148: goto +1319 -> 2467
    //   1151: bipush 78
    //   1153: goto +1314 -> 2467
    //   1156: sipush 255
    //   1159: goto +1308 -> 2467
    //   1162: sipush 182
    //   1165: goto +1302 -> 2467
    //   1168: sipush 214
    //   1171: goto +1296 -> 2467
    //   1174: sipush 151
    //   1177: goto +1290 -> 2467
    //   1180: sipush 162
    //   1183: goto +1284 -> 2467
    //   1186: sipush 203
    //   1189: goto +1278 -> 2467
    //   1192: sipush 246
    //   1195: goto +1272 -> 2467
    //   1198: bipush 108
    //   1200: goto +1267 -> 2467
    //   1203: sipush 143
    //   1206: goto +1261 -> 2467
    //   1209: bipush 43
    //   1211: goto +1256 -> 2467
    //   1214: iconst_0
    //   1215: goto +1252 -> 2467
    //   1218: sipush 210
    //   1221: goto +1246 -> 2467
    //   1224: sipush 148
    //   1227: goto +1240 -> 2467
    //   1230: sipush 157
    //   1233: goto +1234 -> 2467
    //   1236: bipush 116
    //   1238: goto +1229 -> 2467
    //   1241: sipush 141
    //   1244: goto +1223 -> 2467
    //   1247: bipush 61
    //   1249: goto +1218 -> 2467
    //   1252: sipush 136
    //   1255: goto +1212 -> 2467
    //   1258: sipush 159
    //   1261: goto +1206 -> 2467
    //   1264: sipush 129
    //   1267: goto +1200 -> 2467
    //   1270: bipush 87
    //   1272: goto +1195 -> 2467
    //   1275: sipush 163
    //   1278: goto +1189 -> 2467
    //   1281: bipush 40
    //   1283: goto +1184 -> 2467
    //   1286: bipush 64
    //   1288: goto +1179 -> 2467
    //   1291: sipush 226
    //   1294: goto +1173 -> 2467
    //   1297: bipush 57
    //   1299: goto +1168 -> 2467
    //   1302: sipush 171
    //   1305: goto +1162 -> 2467
    //   1308: bipush 100
    //   1310: goto +1157 -> 2467
    //   1313: sipush 216
    //   1316: goto +1151 -> 2467
    //   1319: sipush 156
    //   1322: goto +1145 -> 2467
    //   1325: bipush 73
    //   1327: goto +1140 -> 2467
    //   1330: bipush 47
    //   1332: goto +1135 -> 2467
    //   1335: sipush 218
    //   1338: goto +1129 -> 2467
    //   1341: bipush 101
    //   1343: goto +1124 -> 2467
    //   1346: sipush 244
    //   1349: goto +1118 -> 2467
    //   1352: bipush 27
    //   1354: goto +1113 -> 2467
    //   1357: sipush 251
    //   1360: goto +1107 -> 2467
    //   1363: sipush 164
    //   1366: goto +1101 -> 2467
    //   1369: bipush 121
    //   1371: goto +1096 -> 2467
    //   1374: bipush 74
    //   1376: goto +1091 -> 2467
    //   1379: bipush 118
    //   1381: goto +1086 -> 2467
    //   1384: sipush 133
    //   1387: goto +1080 -> 2467
    //   1390: bipush 82
    //   1392: goto +1075 -> 2467
    //   1395: bipush 63
    //   1397: goto +1070 -> 2467
    //   1400: sipush 221
    //   1403: goto +1064 -> 2467
    //   1406: sipush 195
    //   1409: goto +1058 -> 2467
    //   1412: bipush 77
    //   1414: goto +1053 -> 2467
    //   1417: bipush 90
    //   1419: goto +1048 -> 2467
    //   1422: bipush 60
    //   1424: goto +1043 -> 2467
    //   1427: sipush 178
    //   1430: goto +1037 -> 2467
    //   1433: sipush 204
    //   1436: goto +1031 -> 2467
    //   1439: bipush 72
    //   1441: goto +1026 -> 2467
    //   1444: bipush 80
    //   1446: goto +1021 -> 2467
    //   1449: sipush 232
    //   1452: goto +1015 -> 2467
    //   1455: bipush 68
    //   1457: goto +1010 -> 2467
    //   1460: bipush 94
    //   1462: goto +1005 -> 2467
    //   1465: sipush 185
    //   1468: goto +999 -> 2467
    //   1471: sipush 247
    //   1474: goto +993 -> 2467
    //   1477: sipush 197
    //   1480: goto +987 -> 2467
    //   1483: sipush 206
    //   1486: goto +981 -> 2467
    //   1489: bipush 42
    //   1491: goto +976 -> 2467
    //   1494: sipush 175
    //   1497: goto +970 -> 2467
    //   1500: bipush 117
    //   1502: goto +965 -> 2467
    //   1505: bipush 71
    //   1507: goto +960 -> 2467
    //   1510: bipush 23
    //   1512: goto +955 -> 2467
    //   1515: sipush 217
    //   1518: goto +949 -> 2467
    //   1521: bipush 123
    //   1523: goto +944 -> 2467
    //   1526: bipush 44
    //   1528: goto +939 -> 2467
    //   1531: sipush 209
    //   1534: goto +933 -> 2467
    //   1537: sipush 161
    //   1540: goto +927 -> 2467
    //   1543: bipush 33
    //   1545: goto +922 -> 2467
    //   1548: sipush 202
    //   1551: goto +916 -> 2467
    //   1554: bipush 120
    //   1556: goto +911 -> 2467
    //   1559: sipush 132
    //   1562: goto +905 -> 2467
    //   1565: sipush 225
    //   1568: goto +899 -> 2467
    //   1571: sipush 154
    //   1574: goto +893 -> 2467
    //   1577: bipush 55
    //   1579: goto +888 -> 2467
    //   1582: bipush 21
    //   1584: goto +883 -> 2467
    //   1587: bipush 83
    //   1589: goto +878 -> 2467
    //   1592: bipush 125
    //   1594: goto +873 -> 2467
    //   1597: bipush 114
    //   1599: goto +868 -> 2467
    //   1602: bipush 13
    //   1604: goto +863 -> 2467
    //   1607: bipush 67
    //   1609: goto +858 -> 2467
    //   1612: sipush 146
    //   1615: goto +852 -> 2467
    //   1618: bipush 70
    //   1620: goto +847 -> 2467
    //   1623: sipush 166
    //   1626: goto +841 -> 2467
    //   1629: bipush 31
    //   1631: goto +836 -> 2467
    //   1634: bipush 22
    //   1636: goto +831 -> 2467
    //   1639: bipush 28
    //   1641: goto +826 -> 2467
    //   1644: sipush 208
    //   1647: goto +820 -> 2467
    //   1650: bipush 25
    //   1652: goto +815 -> 2467
    //   1655: sipush 147
    //   1658: goto +809 -> 2467
    //   1661: bipush 29
    //   1663: goto +804 -> 2467
    //   1666: sipush 158
    //   1669: goto +798 -> 2467
    //   1672: bipush 92
    //   1674: goto +793 -> 2467
    //   1677: sipush 193
    //   1680: goto +787 -> 2467
    //   1683: bipush 14
    //   1685: goto +782 -> 2467
    //   1688: bipush 109
    //   1690: goto +777 -> 2467
    //   1693: bipush 111
    //   1695: goto +772 -> 2467
    //   1698: bipush 35
    //   1700: goto +767 -> 2467
    //   1703: bipush 69
    //   1705: goto +762 -> 2467
    //   1708: iconst_2
    //   1709: goto +758 -> 2467
    //   1712: sipush 152
    //   1715: goto +752 -> 2467
    //   1718: sipush 250
    //   1721: goto +746 -> 2467
    //   1724: bipush 66
    //   1726: goto +741 -> 2467
    //   1729: sipush 231
    //   1732: goto +735 -> 2467
    //   1735: bipush 65
    //   1737: goto +730 -> 2467
    //   1740: sipush 184
    //   1743: goto +724 -> 2467
    //   1746: bipush 10
    //   1748: goto +719 -> 2467
    //   1751: bipush 104
    //   1753: goto +714 -> 2467
    //   1756: bipush 103
    //   1758: goto +709 -> 2467
    //   1761: sipush 137
    //   1764: goto +703 -> 2467
    //   1767: bipush 11
    //   1769: goto +698 -> 2467
    //   1772: sipush 153
    //   1775: goto +692 -> 2467
    //   1778: sipush 227
    //   1781: goto +686 -> 2467
    //   1784: sipush 194
    //   1787: goto +680 -> 2467
    //   1790: sipush 131
    //   1793: goto +674 -> 2467
    //   1796: bipush 38
    //   1798: goto +669 -> 2467
    //   1801: bipush 8
    //   1803: goto +664 -> 2467
    //   1806: bipush 39
    //   1808: goto +659 -> 2467
    //   1811: bipush 32
    //   1813: goto +654 -> 2467
    //   1816: bipush 26
    //   1818: goto +649 -> 2467
    //   1821: bipush 51
    //   1823: goto +644 -> 2467
    //   1826: sipush 242
    //   1829: goto +638 -> 2467
    //   1832: bipush 106
    //   1834: goto +633 -> 2467
    //   1837: bipush 127
    //   1839: goto +628 -> 2467
    //   1842: sipush 168
    //   1845: goto +622 -> 2467
    //   1848: sipush 201
    //   1851: goto +616 -> 2467
    //   1854: bipush 16
    //   1856: goto +611 -> 2467
    //   1859: bipush 99
    //   1861: goto +606 -> 2467
    //   1864: bipush 18
    //   1866: goto +601 -> 2467
    //   1869: bipush 84
    //   1871: goto +596 -> 2467
    //   1874: bipush 89
    //   1876: goto +591 -> 2467
    //   1879: sipush 198
    //   1882: goto +585 -> 2467
    //   1885: bipush 119
    //   1887: goto +580 -> 2467
    //   1890: bipush 97
    //   1892: goto +575 -> 2467
    //   1895: sipush 245
    //   1898: goto +569 -> 2467
    //   1901: bipush 20
    //   1903: goto +564 -> 2467
    //   1906: bipush 19
    //   1908: goto +559 -> 2467
    //   1911: sipush 135
    //   1914: goto +553 -> 2467
    //   1917: sipush 130
    //   1920: goto +547 -> 2467
    //   1923: sipush 229
    //   1926: goto +541 -> 2467
    //   1929: sipush 150
    //   1932: goto +535 -> 2467
    //   1935: iconst_4
    //   1936: goto +531 -> 2467
    //   1939: bipush 102
    //   1941: goto +526 -> 2467
    //   1944: sipush 249
    //   1947: goto +520 -> 2467
    //   1950: sipush 212
    //   1953: goto +514 -> 2467
    //   1956: bipush 48
    //   1958: goto +509 -> 2467
    //   1961: sipush 240
    //   1964: goto +503 -> 2467
    //   1967: sipush 207
    //   1970: goto +497 -> 2467
    //   1973: sipush 142
    //   1976: goto +491 -> 2467
    //   1979: sipush 177
    //   1982: goto +485 -> 2467
    //   1985: bipush 9
    //   1987: goto +480 -> 2467
    //   1990: sipush 155
    //   1993: goto +474 -> 2467
    //   1996: bipush 93
    //   1998: goto +469 -> 2467
    //   2001: sipush 169
    //   2004: goto +463 -> 2467
    //   2007: sipush 180
    //   2010: goto +457 -> 2467
    //   2013: sipush 174
    //   2016: goto +451 -> 2467
    //   2019: bipush 24
    //   2021: goto +446 -> 2467
    //   2024: sipush 176
    //   2027: goto +440 -> 2467
    //   2030: bipush 46
    //   2032: goto +435 -> 2467
    //   2035: bipush 56
    //   2037: goto +430 -> 2467
    //   2040: bipush 7
    //   2042: goto +425 -> 2467
    //   2045: bipush 110
    //   2047: goto +420 -> 2467
    //   2050: sipush 192
    //   2053: goto +414 -> 2467
    //   2056: bipush 115
    //   2058: goto +409 -> 2467
    //   2061: sipush 235
    //   2064: goto +403 -> 2467
    //   2067: sipush 253
    //   2070: goto +397 -> 2467
    //   2073: bipush 17
    //   2075: goto +392 -> 2467
    //   2078: sipush 230
    //   2081: goto +386 -> 2467
    //   2084: sipush 165
    //   2087: goto +380 -> 2467
    //   2090: sipush 145
    //   2093: goto +374 -> 2467
    //   2096: sipush 254
    //   2099: goto +368 -> 2467
    //   2102: sipush 199
    //   2105: goto +362 -> 2467
    //   2108: bipush 88
    //   2110: goto +357 -> 2467
    //   2113: sipush 183
    //   2116: goto +351 -> 2467
    //   2119: bipush 98
    //   2121: goto +346 -> 2467
    //   2124: sipush 238
    //   2127: goto +340 -> 2467
    //   2130: sipush 248
    //   2133: goto +334 -> 2467
    //   2136: bipush 52
    //   2138: goto +329 -> 2467
    //   2141: bipush 95
    //   2143: goto +324 -> 2467
    //   2146: sipush 215
    //   2149: goto +318 -> 2467
    //   2152: sipush 239
    //   2155: goto +312 -> 2467
    //   2158: bipush 34
    //   2160: goto +307 -> 2467
    //   2163: bipush 122
    //   2165: goto +302 -> 2467
    //   2168: bipush 112
    //   2170: goto +297 -> 2467
    //   2173: bipush 76
    //   2175: goto +292 -> 2467
    //   2178: sipush 223
    //   2181: goto +286 -> 2467
    //   2184: iconst_1
    //   2185: goto +282 -> 2467
    //   2188: sipush 140
    //   2191: goto +276 -> 2467
    //   2194: sipush 224
    //   2197: goto +270 -> 2467
    //   2200: bipush 53
    //   2202: goto +265 -> 2467
    //   2205: sipush 243
    //   2208: goto +259 -> 2467
    //   2211: bipush 6
    //   2213: goto +254 -> 2467
    //   2216: bipush 85
    //   2218: goto +249 -> 2467
    //   2221: bipush 36
    //   2223: goto +244 -> 2467
    //   2226: bipush 45
    //   2228: goto +239 -> 2467
    //   2231: iconst_3
    //   2232: goto +235 -> 2467
    //   2235: sipush 219
    //   2238: goto +229 -> 2467
    //   2241: bipush 50
    //   2243: goto +224 -> 2467
    //   2246: bipush 54
    //   2248: goto +219 -> 2467
    //   2251: sipush 228
    //   2254: goto +213 -> 2467
    //   2257: bipush 15
    //   2259: goto +208 -> 2467
    //   2262: bipush 96
    //   2264: goto +203 -> 2467
    //   2267: sipush 252
    //   2270: goto +197 -> 2467
    //   2273: sipush 160
    //   2276: goto +191 -> 2467
    //   2279: sipush 241
    //   2282: goto +185 -> 2467
    //   2285: sipush 144
    //   2288: goto +179 -> 2467
    //   2291: bipush 12
    //   2293: goto +174 -> 2467
    //   2296: sipush 128
    //   2299: goto +168 -> 2467
    //   2302: bipush 59
    //   2304: goto +163 -> 2467
    //   2307: sipush 233
    //   2310: goto +157 -> 2467
    //   2313: sipush 149
    //   2316: goto +151 -> 2467
    //   2319: bipush 113
    //   2321: goto +146 -> 2467
    //   2324: bipush 126
    //   2326: goto +141 -> 2467
    //   2329: sipush 188
    //   2332: goto +135 -> 2467
    //   2335: bipush 124
    //   2337: goto +130 -> 2467
    //   2340: sipush 213
    //   2343: goto +124 -> 2467
    //   2346: bipush 86
    //   2348: goto +119 -> 2467
    //   2351: sipush 200
    //   2354: goto +113 -> 2467
    //   2357: sipush 189
    //   2360: goto +107 -> 2467
    //   2363: iconst_5
    //   2364: goto +103 -> 2467
    //   2367: sipush 139
    //   2370: goto +97 -> 2467
    //   2373: bipush 37
    //   2375: goto +92 -> 2467
    //   2378: sipush 205
    //   2381: goto +86 -> 2467
    //   2384: sipush 191
    //   2387: goto +80 -> 2467
    //   2390: sipush 220
    //   2393: goto +74 -> 2467
    //   2396: bipush 75
    //   2398: goto +69 -> 2467
    //   2401: sipush 173
    //   2404: goto +63 -> 2467
    //   2407: sipush 138
    //   2410: goto +57 -> 2467
    //   2413: bipush 58
    //   2415: goto +52 -> 2467
    //   2418: sipush 134
    //   2421: goto +46 -> 2467
    //   2424: sipush 187
    //   2427: goto +40 -> 2467
    //   2430: sipush 234
    //   2433: goto +34 -> 2467
    //   2436: sipush 237
    //   2439: goto +28 -> 2467
    //   2442: bipush 30
    //   2444: goto +23 -> 2467
    //   2447: sipush 172
    //   2450: goto +17 -> 2467
    //   2453: sipush 167
    //   2456: goto +11 -> 2467
    //   2459: sipush 181
    //   2462: goto +5 -> 2467
    //   2465: bipush 105
    //   2467: istore 4
    //   2469: iload_1
    //   2470: sipush 255
    //   2473: iand
    //   2474: iload 4
    //   2476: isub
    //   2477: istore 5
    //   2479: iload 5
    //   2481: ifge +9 -> 2490
    //   2484: wide
    //   2490: iload_1
    //   2491: ldc 6
    //   2493: iand
    //   2494: bipush 8
    //   2496: iushr
    //   2497: iload 4
    //   2499: isub
    //   2500: istore 6
    //   2502: iload 6
    //   2504: ifge +9 -> 2513
    //   2507: wide
    //   2513: iconst_0
    //   2514: istore 7
    //   2516: goto +75 -> 2591
    //   2519: iload 7
    //   2521: iconst_2
    //   2522: irem
    //   2523: istore 8
    //   2525: aload_3
    //   2526: iload 7
    //   2528: dup2
    //   2529: caload
    //   2530: iload 8
    //   2532: ifne +31 -> 2563
    //   2535: iload 5
    //   2537: ixor
    //   2538: i2c
    //   2539: castore
    //   2540: iload 5
    //   2542: iconst_3
    //   2543: iushr
    //   2544: iload 5
    //   2546: iconst_5
    //   2547: ishl
    //   2548: ior
    //   2549: aload_3
    //   2550: iload 7
    //   2552: caload
    //   2553: ixor
    //   2554: sipush 255
    //   2557: iand
    //   2558: istore 5
    //   2560: goto +28 -> 2588
    //   2563: iload 6
    //   2565: ixor
    //   2566: i2c
    //   2567: castore
    //   2568: iload 6
    //   2570: iconst_3
    //   2571: iushr
    //   2572: iload 6
    //   2574: iconst_5
    //   2575: ishl
    //   2576: ior
    //   2577: aload_3
    //   2578: iload 7
    //   2580: caload
    //   2581: ixor
    //   2582: sipush 255
    //   2585: iand
    //   2586: istore 6
    //   2588: iinc 7 1
    //   2591: iload 7
    //   2593: aload_3
    //   2594: arraylength
    //   2595: if_icmplt -76 -> 2519
    //   2598: getstatic 248	a:r	[Ljava/lang/String;
    //   2601: iload_2
    //   2602: new 108	java/lang/String
    //   2605: dup
    //   2606: aload_3
    //   2607: invokespecial 246	java/lang/String:<init>	([C)V
    //   2610: invokevirtual 239	java/lang/String:intern	()Ljava/lang/String;
    //   2613: aastore
    //   2614: getstatic 248	a:r	[Ljava/lang/String;
    //   2617: iload_2
    //   2618: aaload
    //   2619: areturn
  }
}


/* Location:              D:\COMP3331\NonObf\cdht.jar!\a.class
 * Java compiler version: 8 (52.0)
 * JD-Core Version:       0.7.1
 */