class b
  extends Thread
{
  private static final String[] a;
  private static final String[] b;
  
  /* Error */
  public void run()
  {
    // Byte code:
    //   0: getstatic 147	c:b	Z
    //   3: aconst_null
    //   4: astore_2
    //   5: istore_1
    //   6: new 10	java/net/ServerSocket
    //   9: dup
    //   10: ldc 1
    //   12: getstatic 11	a:a	I
    //   15: iadd
    //   16: invokespecial 12	java/net/ServerSocket:<init>	(I)V
    //   19: astore_2
    //   20: goto +11 -> 31
    //   23: astore_3
    //   24: getstatic 14	java/lang/System:out	Ljava/io/PrintStream;
    //   27: aload_3
    //   28: invokevirtual 15	java/io/PrintStream:println	(Ljava/lang/Object;)V
    //   31: aload_2
    //   32: invokevirtual 16	java/net/ServerSocket:accept	()Ljava/net/Socket;
    //   35: astore_3
    //   36: new 17	java/io/BufferedReader
    //   39: dup
    //   40: new 18	java/io/InputStreamReader
    //   43: dup
    //   44: aload_3
    //   45: invokevirtual 19	java/net/Socket:getInputStream	()Ljava/io/InputStream;
    //   48: invokespecial 20	java/io/InputStreamReader:<init>	(Ljava/io/InputStream;)V
    //   51: invokespecial 21	java/io/BufferedReader:<init>	(Ljava/io/Reader;)V
    //   54: astore 4
    //   56: aload 4
    //   58: invokevirtual 22	java/io/BufferedReader:readLine	()Ljava/lang/String;
    //   61: astore 5
    //   63: aload 5
    //   65: ldc 2
    //   67: invokevirtual 23	java/lang/String:split	(Ljava/lang/String;)[Ljava/lang/String;
    //   70: astore 6
    //   72: aload 6
    //   74: iconst_0
    //   75: aaload
    //   76: sipush 11178
    //   79: sipush 31061
    //   82: invokestatic 165	b:a	(II)Ljava/lang/String;
    //   85: invokevirtual 24	java/lang/String:equals	(Ljava/lang/Object;)Z
    //   88: ifeq +78 -> 166
    //   91: getstatic 14	java/lang/System:out	Ljava/io/PrintStream;
    //   94: new 25	java/lang/StringBuilder
    //   97: dup
    //   98: invokespecial 26	java/lang/StringBuilder:<init>	()V
    //   101: sipush 11175
    //   104: sipush 18049
    //   107: invokestatic 165	b:a	(II)Ljava/lang/String;
    //   110: invokevirtual 27	java/lang/StringBuilder:append	(Ljava/lang/String;)Ljava/lang/StringBuilder;
    //   113: aload 6
    //   115: iconst_2
    //   116: aaload
    //   117: invokevirtual 27	java/lang/StringBuilder:append	(Ljava/lang/String;)Ljava/lang/StringBuilder;
    //   120: sipush 11190
    //   123: sipush 11197
    //   126: invokestatic 165	b:a	(II)Ljava/lang/String;
    //   129: invokevirtual 27	java/lang/StringBuilder:append	(Ljava/lang/String;)Ljava/lang/StringBuilder;
    //   132: aload 6
    //   134: iconst_1
    //   135: aaload
    //   136: invokevirtual 27	java/lang/StringBuilder:append	(Ljava/lang/String;)Ljava/lang/StringBuilder;
    //   139: ldc 3
    //   141: invokevirtual 27	java/lang/StringBuilder:append	(Ljava/lang/String;)Ljava/lang/StringBuilder;
    //   144: invokevirtual 28	java/lang/StringBuilder:toString	()Ljava/lang/String;
    //   147: invokevirtual 29	java/io/PrintStream:println	(Ljava/lang/String;)V
    //   150: iload_1
    //   151: ifne +104 -> 255
    //   154: goto +4 -> 158
    //   157: athrow
    //   158: iload_1
    //   159: ifeq +1193 -> 1352
    //   162: goto +4 -> 166
    //   165: athrow
    //   166: aload 6
    //   168: iconst_0
    //   169: aaload
    //   170: sipush 11188
    //   173: sipush 7831
    //   176: invokestatic 165	b:a	(II)Ljava/lang/String;
    //   179: invokevirtual 24	java/lang/String:equals	(Ljava/lang/Object;)Z
    //   182: ifeq +73 -> 255
    //   185: goto +4 -> 189
    //   188: athrow
    //   189: new 30	java/io/DataOutputStream
    //   192: dup
    //   193: aload_3
    //   194: invokevirtual 31	java/net/Socket:getOutputStream	()Ljava/io/OutputStream;
    //   197: invokespecial 32	java/io/DataOutputStream:<init>	(Ljava/io/OutputStream;)V
    //   200: astore 7
    //   202: aload 7
    //   204: new 25	java/lang/StringBuilder
    //   207: dup
    //   208: invokespecial 26	java/lang/StringBuilder:<init>	()V
    //   211: sipush 11171
    //   214: sipush 62964
    //   217: invokestatic 165	b:a	(II)Ljava/lang/String;
    //   220: invokevirtual 27	java/lang/StringBuilder:append	(Ljava/lang/String;)Ljava/lang/StringBuilder;
    //   223: getstatic 33	a:b	I
    //   226: invokevirtual 34	java/lang/StringBuilder:append	(I)Ljava/lang/StringBuilder;
    //   229: ldc 2
    //   231: invokevirtual 27	java/lang/StringBuilder:append	(Ljava/lang/String;)Ljava/lang/StringBuilder;
    //   234: getstatic 35	a:c	I
    //   237: invokevirtual 34	java/lang/StringBuilder:append	(I)Ljava/lang/StringBuilder;
    //   240: ldc 4
    //   242: invokevirtual 27	java/lang/StringBuilder:append	(Ljava/lang/String;)Ljava/lang/StringBuilder;
    //   245: invokevirtual 28	java/lang/StringBuilder:toString	()Ljava/lang/String;
    //   248: invokevirtual 36	java/io/DataOutputStream:writeBytes	(Ljava/lang/String;)V
    //   251: iload_1
    //   252: ifeq +1100 -> 1352
    //   255: aload 6
    //   257: iconst_0
    //   258: aaload
    //   259: sipush 11180
    //   262: sipush 26623
    //   265: invokestatic 165	b:a	(II)Ljava/lang/String;
    //   268: invokevirtual 24	java/lang/String:equals	(Ljava/lang/Object;)Z
    //   271: ifeq +592 -> 863
    //   274: aload 6
    //   276: iconst_3
    //   277: aaload
    //   278: invokestatic 37	java/lang/Integer:parseInt	(Ljava/lang/String;)I
    //   281: istore 7
    //   283: getstatic 14	java/lang/System:out	Ljava/io/PrintStream;
    //   286: new 25	java/lang/StringBuilder
    //   289: dup
    //   290: invokespecial 26	java/lang/StringBuilder:<init>	()V
    //   293: sipush 11170
    //   296: sipush 45302
    //   299: invokestatic 165	b:a	(II)Ljava/lang/String;
    //   302: invokevirtual 27	java/lang/StringBuilder:append	(Ljava/lang/String;)Ljava/lang/StringBuilder;
    //   305: iload 7
    //   307: invokevirtual 34	java/lang/StringBuilder:append	(I)Ljava/lang/StringBuilder;
    //   310: sipush 11169
    //   313: sipush 1877
    //   316: invokestatic 165	b:a	(II)Ljava/lang/String;
    //   319: invokevirtual 27	java/lang/StringBuilder:append	(Ljava/lang/String;)Ljava/lang/StringBuilder;
    //   322: invokevirtual 28	java/lang/StringBuilder:toString	()Ljava/lang/String;
    //   325: invokevirtual 29	java/io/PrintStream:println	(Ljava/lang/String;)V
    //   328: new 30	java/io/DataOutputStream
    //   331: dup
    //   332: aload_3
    //   333: invokevirtual 31	java/net/Socket:getOutputStream	()Ljava/io/OutputStream;
    //   336: invokespecial 32	java/io/DataOutputStream:<init>	(Ljava/io/OutputStream;)V
    //   339: astore 8
    //   341: aload 8
    //   343: sipush 11168
    //   346: sipush 63256
    //   349: invokestatic 165	b:a	(II)Ljava/lang/String;
    //   352: invokevirtual 36	java/io/DataOutputStream:writeBytes	(Ljava/lang/String;)V
    //   355: iload 7
    //   357: getstatic 35	a:c	I
    //   360: if_icmpne +191 -> 551
    //   363: iload 7
    //   365: getstatic 38	a:e	I
    //   368: if_icmpne +183 -> 551
    //   371: goto +4 -> 375
    //   374: athrow
    //   375: getstatic 39	a:d	I
    //   378: putstatic 35	a:c	I
    //   381: getstatic 33	a:b	I
    //   384: putstatic 38	a:e	I
    //   387: getstatic 14	java/lang/System:out	Ljava/io/PrintStream;
    //   390: new 25	java/lang/StringBuilder
    //   393: dup
    //   394: invokespecial 26	java/lang/StringBuilder:<init>	()V
    //   397: sipush 11187
    //   400: sipush 11879
    //   403: invokestatic 165	b:a	(II)Ljava/lang/String;
    //   406: invokevirtual 27	java/lang/StringBuilder:append	(Ljava/lang/String;)Ljava/lang/StringBuilder;
    //   409: getstatic 33	a:b	I
    //   412: invokevirtual 34	java/lang/StringBuilder:append	(I)Ljava/lang/StringBuilder;
    //   415: ldc 3
    //   417: invokevirtual 27	java/lang/StringBuilder:append	(Ljava/lang/String;)Ljava/lang/StringBuilder;
    //   420: invokevirtual 28	java/lang/StringBuilder:toString	()Ljava/lang/String;
    //   423: invokevirtual 29	java/io/PrintStream:println	(Ljava/lang/String;)V
    //   426: getstatic 14	java/lang/System:out	Ljava/io/PrintStream;
    //   429: new 25	java/lang/StringBuilder
    //   432: dup
    //   433: invokespecial 26	java/lang/StringBuilder:<init>	()V
    //   436: sipush 11198
    //   439: sipush 24600
    //   442: invokestatic 165	b:a	(II)Ljava/lang/String;
    //   445: invokevirtual 27	java/lang/StringBuilder:append	(Ljava/lang/String;)Ljava/lang/StringBuilder;
    //   448: getstatic 35	a:c	I
    //   451: invokevirtual 34	java/lang/StringBuilder:append	(I)Ljava/lang/StringBuilder;
    //   454: ldc 3
    //   456: invokevirtual 27	java/lang/StringBuilder:append	(Ljava/lang/String;)Ljava/lang/StringBuilder;
    //   459: invokevirtual 28	java/lang/StringBuilder:toString	()Ljava/lang/String;
    //   462: invokevirtual 29	java/io/PrintStream:println	(Ljava/lang/String;)V
    //   465: getstatic 14	java/lang/System:out	Ljava/io/PrintStream;
    //   468: new 25	java/lang/StringBuilder
    //   471: dup
    //   472: invokespecial 26	java/lang/StringBuilder:<init>	()V
    //   475: sipush 11192
    //   478: sipush 14833
    //   481: invokestatic 165	b:a	(II)Ljava/lang/String;
    //   484: invokevirtual 27	java/lang/StringBuilder:append	(Ljava/lang/String;)Ljava/lang/StringBuilder;
    //   487: getstatic 39	a:d	I
    //   490: invokevirtual 34	java/lang/StringBuilder:append	(I)Ljava/lang/StringBuilder;
    //   493: ldc 3
    //   495: invokevirtual 27	java/lang/StringBuilder:append	(Ljava/lang/String;)Ljava/lang/StringBuilder;
    //   498: invokevirtual 28	java/lang/StringBuilder:toString	()Ljava/lang/String;
    //   501: invokevirtual 29	java/io/PrintStream:println	(Ljava/lang/String;)V
    //   504: getstatic 14	java/lang/System:out	Ljava/io/PrintStream;
    //   507: new 25	java/lang/StringBuilder
    //   510: dup
    //   511: invokespecial 26	java/lang/StringBuilder:<init>	()V
    //   514: sipush 11172
    //   517: sipush 58172
    //   520: invokestatic 165	b:a	(II)Ljava/lang/String;
    //   523: invokevirtual 27	java/lang/StringBuilder:append	(Ljava/lang/String;)Ljava/lang/StringBuilder;
    //   526: getstatic 38	a:e	I
    //   529: invokevirtual 34	java/lang/StringBuilder:append	(I)Ljava/lang/StringBuilder;
    //   532: ldc 3
    //   534: invokevirtual 27	java/lang/StringBuilder:append	(Ljava/lang/String;)Ljava/lang/StringBuilder;
    //   537: invokevirtual 28	java/lang/StringBuilder:toString	()Ljava/lang/String;
    //   540: invokevirtual 29	java/io/PrintStream:println	(Ljava/lang/String;)V
    //   543: iload_1
    //   544: ifeq +315 -> 859
    //   547: goto +4 -> 551
    //   550: athrow
    //   551: iload 7
    //   553: getstatic 33	a:b	I
    //   556: if_icmpeq +19 -> 575
    //   559: goto +4 -> 563
    //   562: athrow
    //   563: iload 7
    //   565: getstatic 35	a:c	I
    //   568: if_icmpne +139 -> 707
    //   571: goto +4 -> 575
    //   574: athrow
    //   575: iload 7
    //   577: getstatic 33	a:b	I
    //   580: if_icmpne +31 -> 611
    //   583: goto +4 -> 587
    //   586: athrow
    //   587: getstatic 35	a:c	I
    //   590: putstatic 33	a:b	I
    //   593: aload 6
    //   595: iconst_2
    //   596: aaload
    //   597: invokestatic 37	java/lang/Integer:parseInt	(Ljava/lang/String;)I
    //   600: putstatic 35	a:c	I
    //   603: iload_1
    //   604: ifeq +21 -> 625
    //   607: goto +4 -> 611
    //   610: athrow
    //   611: aload 6
    //   613: iconst_1
    //   614: aaload
    //   615: invokestatic 37	java/lang/Integer:parseInt	(Ljava/lang/String;)I
    //   618: putstatic 35	a:c	I
    //   621: goto +4 -> 625
    //   624: athrow
    //   625: getstatic 14	java/lang/System:out	Ljava/io/PrintStream;
    //   628: new 25	java/lang/StringBuilder
    //   631: dup
    //   632: invokespecial 26	java/lang/StringBuilder:<init>	()V
    //   635: sipush 11179
    //   638: sipush 32348
    //   641: invokestatic 165	b:a	(II)Ljava/lang/String;
    //   644: invokevirtual 27	java/lang/StringBuilder:append	(Ljava/lang/String;)Ljava/lang/StringBuilder;
    //   647: getstatic 33	a:b	I
    //   650: invokevirtual 34	java/lang/StringBuilder:append	(I)Ljava/lang/StringBuilder;
    //   653: ldc 3
    //   655: invokevirtual 27	java/lang/StringBuilder:append	(Ljava/lang/String;)Ljava/lang/StringBuilder;
    //   658: invokevirtual 28	java/lang/StringBuilder:toString	()Ljava/lang/String;
    //   661: invokevirtual 29	java/io/PrintStream:println	(Ljava/lang/String;)V
    //   664: getstatic 14	java/lang/System:out	Ljava/io/PrintStream;
    //   667: new 25	java/lang/StringBuilder
    //   670: dup
    //   671: invokespecial 26	java/lang/StringBuilder:<init>	()V
    //   674: sipush 11199
    //   677: sipush 64824
    //   680: invokestatic 165	b:a	(II)Ljava/lang/String;
    //   683: invokevirtual 27	java/lang/StringBuilder:append	(Ljava/lang/String;)Ljava/lang/StringBuilder;
    //   686: getstatic 35	a:c	I
    //   689: invokevirtual 34	java/lang/StringBuilder:append	(I)Ljava/lang/StringBuilder;
    //   692: ldc 3
    //   694: invokevirtual 27	java/lang/StringBuilder:append	(Ljava/lang/String;)Ljava/lang/StringBuilder;
    //   697: invokevirtual 28	java/lang/StringBuilder:toString	()Ljava/lang/String;
    //   700: invokevirtual 29	java/io/PrintStream:println	(Ljava/lang/String;)V
    //   703: iload_1
    //   704: ifeq +155 -> 859
    //   707: iload 7
    //   709: getstatic 39	a:d	I
    //   712: if_icmpeq +19 -> 731
    //   715: goto +4 -> 719
    //   718: athrow
    //   719: iload 7
    //   721: getstatic 38	a:e	I
    //   724: if_icmpne +135 -> 859
    //   727: goto +4 -> 731
    //   730: athrow
    //   731: iload 7
    //   733: getstatic 39	a:d	I
    //   736: if_icmpne +31 -> 767
    //   739: goto +4 -> 743
    //   742: athrow
    //   743: getstatic 38	a:e	I
    //   746: putstatic 39	a:d	I
    //   749: aload 6
    //   751: iconst_2
    //   752: aaload
    //   753: invokestatic 37	java/lang/Integer:parseInt	(Ljava/lang/String;)I
    //   756: putstatic 38	a:e	I
    //   759: iload_1
    //   760: ifeq +21 -> 781
    //   763: goto +4 -> 767
    //   766: athrow
    //   767: aload 6
    //   769: iconst_1
    //   770: aaload
    //   771: invokestatic 37	java/lang/Integer:parseInt	(Ljava/lang/String;)I
    //   774: putstatic 38	a:e	I
    //   777: goto +4 -> 781
    //   780: athrow
    //   781: getstatic 14	java/lang/System:out	Ljava/io/PrintStream;
    //   784: new 25	java/lang/StringBuilder
    //   787: dup
    //   788: invokespecial 26	java/lang/StringBuilder:<init>	()V
    //   791: sipush 11183
    //   794: sipush 14780
    //   797: invokestatic 165	b:a	(II)Ljava/lang/String;
    //   800: invokevirtual 27	java/lang/StringBuilder:append	(Ljava/lang/String;)Ljava/lang/StringBuilder;
    //   803: getstatic 39	a:d	I
    //   806: invokevirtual 34	java/lang/StringBuilder:append	(I)Ljava/lang/StringBuilder;
    //   809: ldc 3
    //   811: invokevirtual 27	java/lang/StringBuilder:append	(Ljava/lang/String;)Ljava/lang/StringBuilder;
    //   814: invokevirtual 28	java/lang/StringBuilder:toString	()Ljava/lang/String;
    //   817: invokevirtual 29	java/io/PrintStream:println	(Ljava/lang/String;)V
    //   820: getstatic 14	java/lang/System:out	Ljava/io/PrintStream;
    //   823: new 25	java/lang/StringBuilder
    //   826: dup
    //   827: invokespecial 26	java/lang/StringBuilder:<init>	()V
    //   830: sipush 11176
    //   833: sipush 60845
    //   836: invokestatic 165	b:a	(II)Ljava/lang/String;
    //   839: invokevirtual 27	java/lang/StringBuilder:append	(Ljava/lang/String;)Ljava/lang/StringBuilder;
    //   842: getstatic 38	a:e	I
    //   845: invokevirtual 34	java/lang/StringBuilder:append	(I)Ljava/lang/StringBuilder;
    //   848: ldc 3
    //   850: invokevirtual 27	java/lang/StringBuilder:append	(Ljava/lang/String;)Ljava/lang/StringBuilder;
    //   853: invokevirtual 28	java/lang/StringBuilder:toString	()Ljava/lang/String;
    //   856: invokevirtual 29	java/io/PrintStream:println	(Ljava/lang/String;)V
    //   859: iload_1
    //   860: ifeq +492 -> 1352
    //   863: aload 6
    //   865: iconst_0
    //   866: aaload
    //   867: sipush 11182
    //   870: sipush 17829
    //   873: invokestatic 165	b:a	(II)Ljava/lang/String;
    //   876: invokevirtual 24	java/lang/String:equals	(Ljava/lang/Object;)Z
    //   879: ifeq +473 -> 1352
    //   882: goto +4 -> 886
    //   885: athrow
    //   886: aload 6
    //   888: iconst_1
    //   889: aaload
    //   890: astore 7
    //   892: aload 6
    //   894: iconst_2
    //   895: aaload
    //   896: astore 8
    //   898: aload 6
    //   900: iconst_3
    //   901: aaload
    //   902: astore 9
    //   904: aload 7
    //   906: invokestatic 37	java/lang/Integer:parseInt	(Ljava/lang/String;)I
    //   909: sipush 256
    //   912: irem
    //   913: istore 10
    //   915: getstatic 11	a:a	I
    //   918: aload 8
    //   920: invokestatic 37	java/lang/Integer:parseInt	(Ljava/lang/String;)I
    //   923: isub
    //   924: sipush 256
    //   927: iadd
    //   928: sipush 256
    //   931: irem
    //   932: getstatic 11	a:a	I
    //   935: iload 10
    //   937: isub
    //   938: sipush 256
    //   941: iadd
    //   942: sipush 256
    //   945: irem
    //   946: if_icmple +210 -> 1156
    //   949: getstatic 14	java/lang/System:out	Ljava/io/PrintStream;
    //   952: new 25	java/lang/StringBuilder
    //   955: dup
    //   956: invokespecial 26	java/lang/StringBuilder:<init>	()V
    //   959: sipush 11191
    //   962: sipush 49619
    //   965: invokestatic 165	b:a	(II)Ljava/lang/String;
    //   968: invokevirtual 27	java/lang/StringBuilder:append	(Ljava/lang/String;)Ljava/lang/StringBuilder;
    //   971: aload 7
    //   973: invokevirtual 27	java/lang/StringBuilder:append	(Ljava/lang/String;)Ljava/lang/StringBuilder;
    //   976: sipush 11184
    //   979: sipush 571
    //   982: invokestatic 165	b:a	(II)Ljava/lang/String;
    //   985: invokevirtual 27	java/lang/StringBuilder:append	(Ljava/lang/String;)Ljava/lang/StringBuilder;
    //   988: invokevirtual 28	java/lang/StringBuilder:toString	()Ljava/lang/String;
    //   991: invokevirtual 29	java/io/PrintStream:println	(Ljava/lang/String;)V
    //   994: getstatic 14	java/lang/System:out	Ljava/io/PrintStream;
    //   997: new 25	java/lang/StringBuilder
    //   1000: dup
    //   1001: invokespecial 26	java/lang/StringBuilder:<init>	()V
    //   1004: sipush 11186
    //   1007: sipush 28256
    //   1010: invokestatic 165	b:a	(II)Ljava/lang/String;
    //   1013: invokevirtual 27	java/lang/StringBuilder:append	(Ljava/lang/String;)Ljava/lang/StringBuilder;
    //   1016: aload 9
    //   1018: invokevirtual 27	java/lang/StringBuilder:append	(Ljava/lang/String;)Ljava/lang/StringBuilder;
    //   1021: sipush 11177
    //   1024: sipush 50700
    //   1027: invokestatic 165	b:a	(II)Ljava/lang/String;
    //   1030: invokevirtual 27	java/lang/StringBuilder:append	(Ljava/lang/String;)Ljava/lang/StringBuilder;
    //   1033: invokevirtual 28	java/lang/StringBuilder:toString	()Ljava/lang/String;
    //   1036: invokevirtual 29	java/io/PrintStream:println	(Ljava/lang/String;)V
    //   1039: new 40	java/net/Socket
    //   1042: dup
    //   1043: sipush 11185
    //   1046: sipush 60811
    //   1049: invokestatic 165	b:a	(II)Ljava/lang/String;
    //   1052: invokestatic 41	java/net/InetAddress:getByName	(Ljava/lang/String;)Ljava/net/InetAddress;
    //   1055: ldc 1
    //   1057: aload 9
    //   1059: invokestatic 37	java/lang/Integer:parseInt	(Ljava/lang/String;)I
    //   1062: iadd
    //   1063: invokespecial 42	java/net/Socket:<init>	(Ljava/net/InetAddress;I)V
    //   1066: astore 11
    //   1068: new 30	java/io/DataOutputStream
    //   1071: dup
    //   1072: aload 11
    //   1074: invokevirtual 31	java/net/Socket:getOutputStream	()Ljava/io/OutputStream;
    //   1077: invokespecial 32	java/io/DataOutputStream:<init>	(Ljava/io/OutputStream;)V
    //   1080: astore 12
    //   1082: new 25	java/lang/StringBuilder
    //   1085: dup
    //   1086: invokespecial 26	java/lang/StringBuilder:<init>	()V
    //   1089: sipush 11196
    //   1092: sipush 62416
    //   1095: invokestatic 165	b:a	(II)Ljava/lang/String;
    //   1098: invokevirtual 27	java/lang/StringBuilder:append	(Ljava/lang/String;)Ljava/lang/StringBuilder;
    //   1101: aload 7
    //   1103: invokevirtual 27	java/lang/StringBuilder:append	(Ljava/lang/String;)Ljava/lang/StringBuilder;
    //   1106: ldc 2
    //   1108: invokevirtual 27	java/lang/StringBuilder:append	(Ljava/lang/String;)Ljava/lang/StringBuilder;
    //   1111: getstatic 11	a:a	I
    //   1114: invokevirtual 34	java/lang/StringBuilder:append	(I)Ljava/lang/StringBuilder;
    //   1117: invokevirtual 28	java/lang/StringBuilder:toString	()Ljava/lang/String;
    //   1120: astore 13
    //   1122: aload 12
    //   1124: new 25	java/lang/StringBuilder
    //   1127: dup
    //   1128: invokespecial 26	java/lang/StringBuilder:<init>	()V
    //   1131: aload 13
    //   1133: invokevirtual 27	java/lang/StringBuilder:append	(Ljava/lang/String;)Ljava/lang/StringBuilder;
    //   1136: ldc 4
    //   1138: invokevirtual 27	java/lang/StringBuilder:append	(Ljava/lang/String;)Ljava/lang/StringBuilder;
    //   1141: invokevirtual 28	java/lang/StringBuilder:toString	()Ljava/lang/String;
    //   1144: invokevirtual 36	java/io/DataOutputStream:writeBytes	(Ljava/lang/String;)V
    //   1147: aload 11
    //   1149: invokevirtual 43	java/net/Socket:close	()V
    //   1152: iload_1
    //   1153: ifeq +199 -> 1352
    //   1156: new 40	java/net/Socket
    //   1159: dup
    //   1160: sipush 11189
    //   1163: sipush 45088
    //   1166: invokestatic 165	b:a	(II)Ljava/lang/String;
    //   1169: invokestatic 41	java/net/InetAddress:getByName	(Ljava/lang/String;)Ljava/net/InetAddress;
    //   1172: ldc 1
    //   1174: getstatic 33	a:b	I
    //   1177: iadd
    //   1178: invokespecial 42	java/net/Socket:<init>	(Ljava/net/InetAddress;I)V
    //   1181: astore 11
    //   1183: goto +32 -> 1215
    //   1186: astore 12
    //   1188: new 40	java/net/Socket
    //   1191: dup
    //   1192: sipush 11189
    //   1195: sipush 45088
    //   1198: invokestatic 165	b:a	(II)Ljava/lang/String;
    //   1201: invokestatic 41	java/net/InetAddress:getByName	(Ljava/lang/String;)Ljava/net/InetAddress;
    //   1204: ldc 1
    //   1206: getstatic 35	a:c	I
    //   1209: iadd
    //   1210: invokespecial 42	java/net/Socket:<init>	(Ljava/net/InetAddress;I)V
    //   1213: astore 11
    //   1215: new 30	java/io/DataOutputStream
    //   1218: dup
    //   1219: aload 11
    //   1221: invokevirtual 31	java/net/Socket:getOutputStream	()Ljava/io/OutputStream;
    //   1224: invokespecial 32	java/io/DataOutputStream:<init>	(Ljava/io/OutputStream;)V
    //   1227: astore 12
    //   1229: aload 12
    //   1231: new 25	java/lang/StringBuilder
    //   1234: dup
    //   1235: invokespecial 26	java/lang/StringBuilder:<init>	()V
    //   1238: sipush 11173
    //   1241: sipush 2863
    //   1244: invokestatic 165	b:a	(II)Ljava/lang/String;
    //   1247: invokevirtual 27	java/lang/StringBuilder:append	(Ljava/lang/String;)Ljava/lang/StringBuilder;
    //   1250: aload 7
    //   1252: invokevirtual 27	java/lang/StringBuilder:append	(Ljava/lang/String;)Ljava/lang/StringBuilder;
    //   1255: ldc 2
    //   1257: invokevirtual 27	java/lang/StringBuilder:append	(Ljava/lang/String;)Ljava/lang/StringBuilder;
    //   1260: getstatic 11	a:a	I
    //   1263: invokevirtual 34	java/lang/StringBuilder:append	(I)Ljava/lang/StringBuilder;
    //   1266: ldc 2
    //   1268: invokevirtual 27	java/lang/StringBuilder:append	(Ljava/lang/String;)Ljava/lang/StringBuilder;
    //   1271: aload 9
    //   1273: invokevirtual 27	java/lang/StringBuilder:append	(Ljava/lang/String;)Ljava/lang/StringBuilder;
    //   1276: ldc 4
    //   1278: invokevirtual 27	java/lang/StringBuilder:append	(Ljava/lang/String;)Ljava/lang/StringBuilder;
    //   1281: invokevirtual 28	java/lang/StringBuilder:toString	()Ljava/lang/String;
    //   1284: invokevirtual 36	java/io/DataOutputStream:writeBytes	(Ljava/lang/String;)V
    //   1287: getstatic 14	java/lang/System:out	Ljava/io/PrintStream;
    //   1290: new 25	java/lang/StringBuilder
    //   1293: dup
    //   1294: invokespecial 26	java/lang/StringBuilder:<init>	()V
    //   1297: sipush 11174
    //   1300: sipush 25348
    //   1303: invokestatic 165	b:a	(II)Ljava/lang/String;
    //   1306: invokevirtual 27	java/lang/StringBuilder:append	(Ljava/lang/String;)Ljava/lang/StringBuilder;
    //   1309: aload 7
    //   1311: invokevirtual 27	java/lang/StringBuilder:append	(Ljava/lang/String;)Ljava/lang/StringBuilder;
    //   1314: sipush 11197
    //   1317: sipush 24076
    //   1320: invokestatic 165	b:a	(II)Ljava/lang/String;
    //   1323: invokevirtual 27	java/lang/StringBuilder:append	(Ljava/lang/String;)Ljava/lang/StringBuilder;
    //   1326: invokevirtual 28	java/lang/StringBuilder:toString	()Ljava/lang/String;
    //   1329: invokevirtual 29	java/io/PrintStream:println	(Ljava/lang/String;)V
    //   1332: getstatic 14	java/lang/System:out	Ljava/io/PrintStream;
    //   1335: sipush 11181
    //   1338: sipush 65026
    //   1341: invokestatic 165	b:a	(II)Ljava/lang/String;
    //   1344: invokevirtual 29	java/io/PrintStream:println	(Ljava/lang/String;)V
    //   1347: aload 11
    //   1349: invokevirtual 43	java/net/Socket:close	()V
    //   1352: aload_3
    //   1353: invokevirtual 43	java/net/Socket:close	()V
    //   1356: goto -1325 -> 31
    //   1359: astore_3
    //   1360: getstatic 14	java/lang/System:out	Ljava/io/PrintStream;
    //   1363: aload_3
    //   1364: invokevirtual 15	java/io/PrintStream:println	(Ljava/lang/Object;)V
    //   1367: goto -1336 -> 31
    // Local variable table:
    //   start	length	slot	name	signature
    //   0	1370	0	this	b
    //   5	1148	1	bool	boolean
    //   4	28	2	localServerSocket	java.net.ServerSocket
    //   23	5	3	localIOException1	java.io.IOException
    //   35	1318	3	localSocket1	java.net.Socket
    //   1359	5	3	localIOException2	java.io.IOException
    //   54	3	4	localBufferedReader	java.io.BufferedReader
    //   61	3	5	str1	String
    //   70	829	6	arrayOfString	String[]
    //   200	3	7	localDataOutputStream1	java.io.DataOutputStream
    //   281	456	7	i	int
    //   890	420	7	str2	String
    //   339	580	8	localObject	Object
    //   902	370	9	str3	String
    //   913	25	10	j	int
    //   1066	282	11	localSocket2	java.net.Socket
    //   1080	43	12	localDataOutputStream2	java.io.DataOutputStream
    //   1186	1	12	localConnectException	java.net.ConnectException
    //   1227	3	12	localDataOutputStream3	java.io.DataOutputStream
    //   1120	12	13	str4	String
    //   157	1	20	localIOException3	java.io.IOException
    //   165	1	21	localIOException4	java.io.IOException
    //   188	1	22	localIOException5	java.io.IOException
    //   374	1	23	localIOException6	java.io.IOException
    //   550	1	24	localIOException7	java.io.IOException
    //   562	1	25	localIOException8	java.io.IOException
    //   574	1	26	localIOException9	java.io.IOException
    //   586	1	27	localIOException10	java.io.IOException
    //   610	1	28	localIOException11	java.io.IOException
    //   624	1	29	localIOException12	java.io.IOException
    //   718	1	30	localIOException13	java.io.IOException
    //   730	1	31	localIOException14	java.io.IOException
    //   742	1	32	localIOException15	java.io.IOException
    //   766	1	33	localIOException16	java.io.IOException
    //   780	1	34	localIOException17	java.io.IOException
    //   885	1	35	localIOException18	java.io.IOException
    // Exception table:
    //   from	to	target	type
    //   6	20	23	java/io/IOException
    //   72	154	157	java/io/IOException
    //   91	162	165	java/io/IOException
    //   158	185	188	java/io/IOException
    //   341	371	374	java/io/IOException
    //   363	547	550	java/io/IOException
    //   375	559	562	java/io/IOException
    //   551	571	574	java/io/IOException
    //   563	583	586	java/io/IOException
    //   575	607	610	java/io/IOException
    //   587	621	624	java/io/IOException
    //   625	715	718	java/io/IOException
    //   707	727	730	java/io/IOException
    //   719	739	742	java/io/IOException
    //   731	763	766	java/io/IOException
    //   743	777	780	java/io/IOException
    //   859	882	885	java/io/IOException
    //   1156	1183	1186	java/net/ConnectException
    //   31	1356	1359	java/io/IOException
  }
  
  /* Error */
  private static String a(int arg0, int arg1)
  {
    // Byte code:
    //   0: iload_0
    //   1: sipush 11172
    //   4: ixor
    //   5: ldc 5
    //   7: iand
    //   8: istore_2
    //   9: getstatic 162	b:b	[Ljava/lang/String;
    //   12: iload_2
    //   13: aaload
    //   14: ifnonnull +2600 -> 2614
    //   17: getstatic 150	b:a	[Ljava/lang/String;
    //   20: iload_2
    //   21: aaload
    //   22: invokevirtual 157	java/lang/String:toCharArray	()[C
    //   25: astore_3
    //   26: aload_3
    //   27: iconst_0
    //   28: caload
    //   29: sipush 255
    //   32: iand
    //   33: tableswitch	default:+2431->2464, 0:+1035->1068, 1:+1040->1073, 2:+1045->1078, 3:+1051->1084, 4:+1057->1090, 5:+1062->1095, 6:+1067->1100, 7:+1072->1105, 8:+1078->1111, 9:+1083->1116, 10:+1089->1122, 11:+1095->1128, 12:+1100->1133, 13:+1105->1138, 14:+1111->1144, 15:+1116->1149, 16:+1122->1155, 17:+1128->1161, 18:+1133->1166, 19:+1139->1172, 20:+1143->1176, 21:+1148->1181, 22:+1152->1185, 23:+1158->1191, 24:+1163->1196, 25:+1169->1202, 26:+1175->1208, 27:+1180->1213, 28:+1185->1218, 29:+1191->1224, 30:+1196->1229, 31:+1200->1233, 32:+1206->1239, 33:+1212->1245, 34:+1218->1251, 35:+1224->1257, 36:+1229->1262, 37:+1234->1267, 38:+1239->1272, 39:+1244->1277, 40:+1249->1282, 41:+1255->1288, 42:+1261->1294, 43:+1266->1299, 44:+1272->1305, 45:+1278->1311, 46:+1284->1317, 47:+1289->1322, 48:+1295->1328, 49:+1301->1334, 50:+1306->1339, 51:+1311->1344, 52:+1317->1350, 53:+1323->1356, 54:+1329->1362, 55:+1335->1368, 56:+1341->1374, 57:+1346->1379, 58:+1351->1384, 59:+1357->1390, 60:+1362->1395, 61:+1368->1401, 62:+1373->1406, 63:+1378->1411, 64:+1383->1416, 65:+1388->1421, 66:+1394->1427, 67:+1400->1433, 68:+1405->1438, 69:+1410->1443, 70:+1416->1449, 71:+1422->1455, 72:+1427->1460, 73:+1433->1466, 74:+1438->1471, 75:+1444->1477, 76:+1450->1483, 77:+1456->1489, 78:+1462->1495, 79:+1467->1500, 80:+1472->1505, 81:+1477->1510, 82:+1482->1515, 83:+1487->1520, 84:+1493->1526, 85:+1499->1532, 86:+1505->1538, 87:+1510->1543, 88:+1516->1549, 89:+1522->1555, 90:+1527->1560, 91:+1533->1566, 92:+1539->1572, 93:+1545->1578, 94:+1550->1583, 95:+1556->1589, 96:+1561->1594, 97:+1566->1599, 98:+1572->1605, 99:+1577->1610, 100:+1583->1616, 101:+1589->1622, 102:+1595->1628, 103:+1601->1634, 104:+1606->1639, 105:+1611->1644, 106:+1617->1650, 107:+1622->1655, 108:+1628->1661, 109:+1633->1666, 110:+1638->1671, 111:+1643->1676, 112:+1648->1681, 113:+1653->1686, 114:+1658->1691, 115:+1664->1697, 116:+1670->1703, 117:+1675->1708, 118:+1681->1714, 119:+1686->1719, 120:+1691->1724, 121:+1697->1730, 122:+1703->1736, 123:+1709->1742, 124:+1714->1747, 125:+1720->1753, 126:+1725->1758, 127:+1730->1763, 128:+1736->1769, 129:+1742->1775, 130:+1747->1780, 131:+1753->1786, 132:+1759->1792, 133:+1765->1798, 134:+1770->1803, 135:+1775->1808, 136:+1781->1814, 137:+1787->1820, 138:+1793->1826, 139:+1799->1832, 140:+1804->1837, 141:+1810->1843, 142:+1815->1848, 143:+1821->1854, 144:+1827->1860, 145:+1833->1866, 146:+1838->1871, 147:+1843->1876, 148:+1848->1881, 149:+1853->1886, 150:+1859->1892, 151:+1865->1898, 152:+1869->1902, 153:+1874->1907, 154:+1879->1912, 155:+1885->1918, 156:+1891->1924, 157:+1897->1930, 158:+1903->1936, 159:+1909->1942, 160:+1914->1947, 161:+1919->1952, 162:+1924->1957, 163:+1930->1963, 164:+1935->1968, 165:+1941->1974, 166:+1946->1979, 167:+1951->1984, 168:+1957->1990, 169:+1962->1995, 170:+1967->2000, 171:+1972->2005, 172:+1978->2011, 173:+1983->2016, 174:+1988->2021, 175:+1994->2027, 176:+1999->2032, 177:+2004->2037, 178:+2009->2042, 179:+2014->2047, 180:+2019->2052, 181:+2024->2057, 182:+2029->2062, 183:+2035->2068, 184:+2041->2074, 185:+2046->2079, 186:+2051->2084, 187:+2057->2090, 188:+2063->2096, 189:+2069->2102, 190:+2074->2107, 191:+2080->2113, 192:+2086->2119, 193:+2091->2124, 194:+2096->2129, 195:+2102->2135, 196:+2108->2141, 197:+2113->2146, 198:+2118->2151, 199:+2124->2157, 200:+2130->2163, 201:+2136->2169, 202:+2142->2175, 203:+2146->2179, 204:+2152->2185, 205:+2157->2190, 206:+2162->2195, 207:+2167->2200, 208:+2173->2206, 209:+2179->2212, 210:+2185->2218, 211:+2190->2223, 212:+2196->2229, 213:+2201->2234, 214:+2207->2240, 215:+2213->2246, 216:+2219->2252, 217:+2225->2258, 218:+2231->2264, 219:+2237->2270, 220:+2242->2275, 221:+2247->2280, 222:+2253->2286, 223:+2259->2292, 224:+2264->2297, 225:+2269->2302, 226:+2275->2308, 227:+2281->2314, 228:+2286->2319, 229:+2292->2325, 230:+2297->2330, 231:+2303->2336, 232:+2309->2342, 233:+2314->2347, 234:+2320->2353, 235:+2326->2359, 236:+2331->2364, 237:+2336->2369, 238:+2341->2374, 239:+2345->2378, 240:+2350->2383, 241:+2355->2388, 242:+2360->2393, 243:+2365->2398, 244:+2371->2404, 245:+2377->2410, 246:+2383->2416, 247:+2389->2422, 248:+2394->2427, 249:+2400->2433, 250:+2405->2438, 251:+2410->2443, 252:+2415->2448, 253:+2421->2454, 254:+2426->2459
    //   1068: bipush 23
    //   1070: goto +1397 -> 2467
    //   1073: bipush 83
    //   1075: goto +1392 -> 2467
    //   1078: sipush 237
    //   1081: goto +1386 -> 2467
    //   1084: sipush 139
    //   1087: goto +1380 -> 2467
    //   1090: bipush 92
    //   1092: goto +1375 -> 2467
    //   1095: bipush 67
    //   1097: goto +1370 -> 2467
    //   1100: bipush 25
    //   1102: goto +1365 -> 2467
    //   1105: sipush 254
    //   1108: goto +1359 -> 2467
    //   1111: bipush 113
    //   1113: goto +1354 -> 2467
    //   1116: sipush 227
    //   1119: goto +1348 -> 2467
    //   1122: sipush 233
    //   1125: goto +1342 -> 2467
    //   1128: bipush 65
    //   1130: goto +1337 -> 2467
    //   1133: bipush 102
    //   1135: goto +1332 -> 2467
    //   1138: sipush 212
    //   1141: goto +1326 -> 2467
    //   1144: bipush 76
    //   1146: goto +1321 -> 2467
    //   1149: sipush 210
    //   1152: goto +1315 -> 2467
    //   1155: sipush 187
    //   1158: goto +1309 -> 2467
    //   1161: bipush 10
    //   1163: goto +1304 -> 2467
    //   1166: sipush 199
    //   1169: goto +1298 -> 2467
    //   1172: iconst_3
    //   1173: goto +1294 -> 2467
    //   1176: bipush 28
    //   1178: goto +1289 -> 2467
    //   1181: iconst_0
    //   1182: goto +1285 -> 2467
    //   1185: sipush 144
    //   1188: goto +1279 -> 2467
    //   1191: bipush 24
    //   1193: goto +1274 -> 2467
    //   1196: sipush 182
    //   1199: goto +1268 -> 2467
    //   1202: sipush 170
    //   1205: goto +1262 -> 2467
    //   1208: bipush 123
    //   1210: goto +1257 -> 2467
    //   1213: bipush 95
    //   1215: goto +1252 -> 2467
    //   1218: sipush 176
    //   1221: goto +1246 -> 2467
    //   1224: bipush 97
    //   1226: goto +1241 -> 2467
    //   1229: iconst_5
    //   1230: goto +1237 -> 2467
    //   1233: sipush 149
    //   1236: goto +1231 -> 2467
    //   1239: sipush 230
    //   1242: goto +1225 -> 2467
    //   1245: sipush 171
    //   1248: goto +1219 -> 2467
    //   1251: sipush 140
    //   1254: goto +1213 -> 2467
    //   1257: bipush 59
    //   1259: goto +1208 -> 2467
    //   1262: bipush 14
    //   1264: goto +1203 -> 2467
    //   1267: bipush 56
    //   1269: goto +1198 -> 2467
    //   1272: bipush 81
    //   1274: goto +1193 -> 2467
    //   1277: bipush 6
    //   1279: goto +1188 -> 2467
    //   1282: sipush 156
    //   1285: goto +1182 -> 2467
    //   1288: sipush 186
    //   1291: goto +1176 -> 2467
    //   1294: bipush 85
    //   1296: goto +1171 -> 2467
    //   1299: sipush 131
    //   1302: goto +1165 -> 2467
    //   1305: sipush 244
    //   1308: goto +1159 -> 2467
    //   1311: sipush 153
    //   1314: goto +1153 -> 2467
    //   1317: bipush 118
    //   1319: goto +1148 -> 2467
    //   1322: sipush 180
    //   1325: goto +1142 -> 2467
    //   1328: sipush 197
    //   1331: goto +1136 -> 2467
    //   1334: bipush 26
    //   1336: goto +1131 -> 2467
    //   1339: bipush 120
    //   1341: goto +1126 -> 2467
    //   1344: sipush 221
    //   1347: goto +1120 -> 2467
    //   1350: sipush 235
    //   1353: goto +1114 -> 2467
    //   1356: sipush 150
    //   1359: goto +1108 -> 2467
    //   1362: sipush 207
    //   1365: goto +1102 -> 2467
    //   1368: sipush 169
    //   1371: goto +1096 -> 2467
    //   1374: bipush 12
    //   1376: goto +1091 -> 2467
    //   1379: bipush 20
    //   1381: goto +1086 -> 2467
    //   1384: sipush 240
    //   1387: goto +1080 -> 2467
    //   1390: bipush 15
    //   1392: goto +1075 -> 2467
    //   1395: sipush 195
    //   1398: goto +1069 -> 2467
    //   1401: bipush 82
    //   1403: goto +1064 -> 2467
    //   1406: bipush 86
    //   1408: goto +1059 -> 2467
    //   1411: bipush 37
    //   1413: goto +1054 -> 2467
    //   1416: bipush 13
    //   1418: goto +1049 -> 2467
    //   1421: sipush 183
    //   1424: goto +1043 -> 2467
    //   1427: sipush 194
    //   1430: goto +1037 -> 2467
    //   1433: bipush 78
    //   1435: goto +1032 -> 2467
    //   1438: bipush 70
    //   1440: goto +1027 -> 2467
    //   1443: sipush 155
    //   1446: goto +1021 -> 2467
    //   1449: sipush 193
    //   1452: goto +1015 -> 2467
    //   1455: bipush 108
    //   1457: goto +1010 -> 2467
    //   1460: sipush 200
    //   1463: goto +1004 -> 2467
    //   1466: bipush 41
    //   1468: goto +999 -> 2467
    //   1471: sipush 175
    //   1474: goto +993 -> 2467
    //   1477: sipush 165
    //   1480: goto +987 -> 2467
    //   1483: sipush 135
    //   1486: goto +981 -> 2467
    //   1489: sipush 232
    //   1492: goto +975 -> 2467
    //   1495: bipush 40
    //   1497: goto +970 -> 2467
    //   1500: bipush 51
    //   1502: goto +965 -> 2467
    //   1505: bipush 31
    //   1507: goto +960 -> 2467
    //   1510: bipush 62
    //   1512: goto +955 -> 2467
    //   1515: bipush 17
    //   1517: goto +950 -> 2467
    //   1520: sipush 137
    //   1523: goto +944 -> 2467
    //   1526: sipush 161
    //   1529: goto +938 -> 2467
    //   1532: sipush 224
    //   1535: goto +932 -> 2467
    //   1538: bipush 126
    //   1540: goto +927 -> 2467
    //   1543: sipush 130
    //   1546: goto +921 -> 2467
    //   1549: sipush 238
    //   1552: goto +915 -> 2467
    //   1555: bipush 93
    //   1557: goto +910 -> 2467
    //   1560: sipush 181
    //   1563: goto +904 -> 2467
    //   1566: sipush 177
    //   1569: goto +898 -> 2467
    //   1572: sipush 241
    //   1575: goto +892 -> 2467
    //   1578: bipush 88
    //   1580: goto +887 -> 2467
    //   1583: sipush 154
    //   1586: goto +881 -> 2467
    //   1589: bipush 80
    //   1591: goto +876 -> 2467
    //   1594: bipush 72
    //   1596: goto +871 -> 2467
    //   1599: sipush 201
    //   1602: goto +865 -> 2467
    //   1605: bipush 49
    //   1607: goto +860 -> 2467
    //   1610: sipush 128
    //   1613: goto +854 -> 2467
    //   1616: sipush 141
    //   1619: goto +848 -> 2467
    //   1622: sipush 133
    //   1625: goto +842 -> 2467
    //   1628: sipush 252
    //   1631: goto +836 -> 2467
    //   1634: bipush 116
    //   1636: goto +831 -> 2467
    //   1639: bipush 75
    //   1641: goto +826 -> 2467
    //   1644: sipush 213
    //   1647: goto +820 -> 2467
    //   1650: bipush 127
    //   1652: goto +815 -> 2467
    //   1655: sipush 214
    //   1658: goto +809 -> 2467
    //   1661: bipush 16
    //   1663: goto +804 -> 2467
    //   1666: bipush 55
    //   1668: goto +799 -> 2467
    //   1671: bipush 114
    //   1673: goto +794 -> 2467
    //   1676: bipush 63
    //   1678: goto +789 -> 2467
    //   1681: bipush 45
    //   1683: goto +784 -> 2467
    //   1686: bipush 87
    //   1688: goto +779 -> 2467
    //   1691: sipush 253
    //   1694: goto +773 -> 2467
    //   1697: sipush 160
    //   1700: goto +767 -> 2467
    //   1703: bipush 58
    //   1705: goto +762 -> 2467
    //   1708: sipush 219
    //   1711: goto +756 -> 2467
    //   1714: bipush 21
    //   1716: goto +751 -> 2467
    //   1719: bipush 64
    //   1721: goto +746 -> 2467
    //   1724: sipush 184
    //   1727: goto +740 -> 2467
    //   1730: sipush 248
    //   1733: goto +734 -> 2467
    //   1736: sipush 243
    //   1739: goto +728 -> 2467
    //   1742: bipush 124
    //   1744: goto +723 -> 2467
    //   1747: sipush 158
    //   1750: goto +717 -> 2467
    //   1753: bipush 19
    //   1755: goto +712 -> 2467
    //   1758: bipush 110
    //   1760: goto +707 -> 2467
    //   1763: sipush 234
    //   1766: goto +701 -> 2467
    //   1769: sipush 245
    //   1772: goto +695 -> 2467
    //   1775: bipush 125
    //   1777: goto +690 -> 2467
    //   1780: sipush 225
    //   1783: goto +684 -> 2467
    //   1786: sipush 217
    //   1789: goto +678 -> 2467
    //   1792: sipush 215
    //   1795: goto +672 -> 2467
    //   1798: bipush 35
    //   1800: goto +667 -> 2467
    //   1803: bipush 36
    //   1805: goto +662 -> 2467
    //   1808: sipush 168
    //   1811: goto +656 -> 2467
    //   1814: sipush 147
    //   1817: goto +650 -> 2467
    //   1820: sipush 151
    //   1823: goto +644 -> 2467
    //   1826: sipush 247
    //   1829: goto +638 -> 2467
    //   1832: bipush 30
    //   1834: goto +633 -> 2467
    //   1837: sipush 146
    //   1840: goto +627 -> 2467
    //   1843: bipush 9
    //   1845: goto +622 -> 2467
    //   1848: sipush 204
    //   1851: goto +616 -> 2467
    //   1854: sipush 228
    //   1857: goto +610 -> 2467
    //   1860: sipush 190
    //   1863: goto +604 -> 2467
    //   1866: bipush 44
    //   1868: goto +599 -> 2467
    //   1871: bipush 71
    //   1873: goto +594 -> 2467
    //   1876: bipush 69
    //   1878: goto +589 -> 2467
    //   1881: bipush 77
    //   1883: goto +584 -> 2467
    //   1886: sipush 163
    //   1889: goto +578 -> 2467
    //   1892: sipush 173
    //   1895: goto +572 -> 2467
    //   1898: iconst_4
    //   1899: goto +568 -> 2467
    //   1902: bipush 73
    //   1904: goto +563 -> 2467
    //   1907: bipush 50
    //   1909: goto +558 -> 2467
    //   1912: sipush 159
    //   1915: goto +552 -> 2467
    //   1918: sipush 192
    //   1921: goto +546 -> 2467
    //   1924: sipush 188
    //   1927: goto +540 -> 2467
    //   1930: sipush 236
    //   1933: goto +534 -> 2467
    //   1936: sipush 211
    //   1939: goto +528 -> 2467
    //   1942: bipush 8
    //   1944: goto +523 -> 2467
    //   1947: bipush 90
    //   1949: goto +518 -> 2467
    //   1952: bipush 29
    //   1954: goto +513 -> 2467
    //   1957: sipush 229
    //   1960: goto +507 -> 2467
    //   1963: bipush 66
    //   1965: goto +502 -> 2467
    //   1968: sipush 145
    //   1971: goto +496 -> 2467
    //   1974: bipush 104
    //   1976: goto +491 -> 2467
    //   1979: bipush 84
    //   1981: goto +486 -> 2467
    //   1984: sipush 242
    //   1987: goto +480 -> 2467
    //   1990: bipush 96
    //   1992: goto +475 -> 2467
    //   1995: bipush 38
    //   1997: goto +470 -> 2467
    //   2000: bipush 43
    //   2002: goto +465 -> 2467
    //   2005: sipush 196
    //   2008: goto +459 -> 2467
    //   2011: bipush 74
    //   2013: goto +454 -> 2467
    //   2016: bipush 100
    //   2018: goto +449 -> 2467
    //   2021: sipush 129
    //   2024: goto +443 -> 2467
    //   2027: bipush 61
    //   2029: goto +438 -> 2467
    //   2032: bipush 34
    //   2034: goto +433 -> 2467
    //   2037: bipush 119
    //   2039: goto +428 -> 2467
    //   2042: bipush 32
    //   2044: goto +423 -> 2467
    //   2047: bipush 47
    //   2049: goto +418 -> 2467
    //   2052: bipush 105
    //   2054: goto +413 -> 2467
    //   2057: bipush 111
    //   2059: goto +408 -> 2467
    //   2062: sipush 216
    //   2065: goto +402 -> 2467
    //   2068: sipush 164
    //   2071: goto +396 -> 2467
    //   2074: bipush 101
    //   2076: goto +391 -> 2467
    //   2079: bipush 122
    //   2081: goto +386 -> 2467
    //   2084: sipush 157
    //   2087: goto +380 -> 2467
    //   2090: sipush 251
    //   2093: goto +374 -> 2467
    //   2096: sipush 143
    //   2099: goto +368 -> 2467
    //   2102: bipush 7
    //   2104: goto +363 -> 2467
    //   2107: sipush 136
    //   2110: goto +357 -> 2467
    //   2113: sipush 218
    //   2116: goto +351 -> 2467
    //   2119: bipush 11
    //   2121: goto +346 -> 2467
    //   2124: bipush 57
    //   2126: goto +341 -> 2467
    //   2129: sipush 185
    //   2132: goto +335 -> 2467
    //   2135: sipush 179
    //   2138: goto +329 -> 2467
    //   2141: bipush 99
    //   2143: goto +324 -> 2467
    //   2146: bipush 22
    //   2148: goto +319 -> 2467
    //   2151: sipush 138
    //   2154: goto +313 -> 2467
    //   2157: sipush 246
    //   2160: goto +307 -> 2467
    //   2163: sipush 206
    //   2166: goto +301 -> 2467
    //   2169: sipush 134
    //   2172: goto +295 -> 2467
    //   2175: iconst_1
    //   2176: goto +291 -> 2467
    //   2179: sipush 191
    //   2182: goto +285 -> 2467
    //   2185: bipush 103
    //   2187: goto +280 -> 2467
    //   2190: bipush 60
    //   2192: goto +275 -> 2467
    //   2195: bipush 39
    //   2197: goto +270 -> 2467
    //   2200: sipush 208
    //   2203: goto +264 -> 2467
    //   2206: sipush 189
    //   2209: goto +258 -> 2467
    //   2212: sipush 203
    //   2215: goto +252 -> 2467
    //   2218: bipush 91
    //   2220: goto +247 -> 2467
    //   2223: sipush 222
    //   2226: goto +241 -> 2467
    //   2229: bipush 33
    //   2231: goto +236 -> 2467
    //   2234: sipush 142
    //   2237: goto +230 -> 2467
    //   2240: sipush 205
    //   2243: goto +224 -> 2467
    //   2246: sipush 255
    //   2249: goto +218 -> 2467
    //   2252: sipush 174
    //   2255: goto +212 -> 2467
    //   2258: sipush 162
    //   2261: goto +206 -> 2467
    //   2264: sipush 249
    //   2267: goto +200 -> 2467
    //   2270: bipush 68
    //   2272: goto +195 -> 2467
    //   2275: bipush 27
    //   2277: goto +190 -> 2467
    //   2280: sipush 231
    //   2283: goto +184 -> 2467
    //   2286: sipush 167
    //   2289: goto +178 -> 2467
    //   2292: bipush 107
    //   2294: goto +173 -> 2467
    //   2297: bipush 106
    //   2299: goto +168 -> 2467
    //   2302: sipush 250
    //   2305: goto +162 -> 2467
    //   2308: sipush 223
    //   2311: goto +156 -> 2467
    //   2314: bipush 46
    //   2316: goto +151 -> 2467
    //   2319: sipush 220
    //   2322: goto +145 -> 2467
    //   2325: bipush 48
    //   2327: goto +140 -> 2467
    //   2330: sipush 226
    //   2333: goto +134 -> 2467
    //   2336: sipush 152
    //   2339: goto +128 -> 2467
    //   2342: bipush 98
    //   2344: goto +123 -> 2467
    //   2347: sipush 198
    //   2350: goto +117 -> 2467
    //   2353: sipush 148
    //   2356: goto +111 -> 2467
    //   2359: bipush 109
    //   2361: goto +106 -> 2467
    //   2364: bipush 94
    //   2366: goto +101 -> 2467
    //   2369: bipush 79
    //   2371: goto +96 -> 2467
    //   2374: iconst_2
    //   2375: goto +92 -> 2467
    //   2378: bipush 117
    //   2380: goto +87 -> 2467
    //   2383: bipush 112
    //   2385: goto +82 -> 2467
    //   2388: bipush 53
    //   2390: goto +77 -> 2467
    //   2393: bipush 121
    //   2395: goto +72 -> 2467
    //   2398: sipush 239
    //   2401: goto +66 -> 2467
    //   2404: sipush 172
    //   2407: goto +60 -> 2467
    //   2410: sipush 209
    //   2413: goto +54 -> 2467
    //   2416: sipush 178
    //   2419: goto +48 -> 2467
    //   2422: bipush 18
    //   2424: goto +43 -> 2467
    //   2427: sipush 202
    //   2430: goto +37 -> 2467
    //   2433: bipush 89
    //   2435: goto +32 -> 2467
    //   2438: bipush 54
    //   2440: goto +27 -> 2467
    //   2443: bipush 115
    //   2445: goto +22 -> 2467
    //   2448: sipush 166
    //   2451: goto +16 -> 2467
    //   2454: bipush 42
    //   2456: goto +11 -> 2467
    //   2459: bipush 52
    //   2461: goto +6 -> 2467
    //   2464: sipush 132
    //   2467: istore 4
    //   2469: iload_1
    //   2470: sipush 255
    //   2473: iand
    //   2474: iload 4
    //   2476: isub
    //   2477: istore 5
    //   2479: iload 5
    //   2481: ifge +9 -> 2490
    //   2484: wide
    //   2490: iload_1
    //   2491: ldc 5
    //   2493: iand
    //   2494: bipush 8
    //   2496: iushr
    //   2497: iload 4
    //   2499: isub
    //   2500: istore 6
    //   2502: iload 6
    //   2504: ifge +9 -> 2513
    //   2507: wide
    //   2513: iconst_0
    //   2514: istore 7
    //   2516: goto +75 -> 2591
    //   2519: iload 7
    //   2521: iconst_2
    //   2522: irem
    //   2523: istore 8
    //   2525: aload_3
    //   2526: iload 7
    //   2528: dup2
    //   2529: caload
    //   2530: iload 8
    //   2532: ifne +31 -> 2563
    //   2535: iload 5
    //   2537: ixor
    //   2538: i2c
    //   2539: castore
    //   2540: iload 5
    //   2542: iconst_3
    //   2543: iushr
    //   2544: iload 5
    //   2546: iconst_5
    //   2547: ishl
    //   2548: ior
    //   2549: aload_3
    //   2550: iload 7
    //   2552: caload
    //   2553: ixor
    //   2554: sipush 255
    //   2557: iand
    //   2558: istore 5
    //   2560: goto +28 -> 2588
    //   2563: iload 6
    //   2565: ixor
    //   2566: i2c
    //   2567: castore
    //   2568: iload 6
    //   2570: iconst_3
    //   2571: iushr
    //   2572: iload 6
    //   2574: iconst_5
    //   2575: ishl
    //   2576: ior
    //   2577: aload_3
    //   2578: iload 7
    //   2580: caload
    //   2581: ixor
    //   2582: sipush 255
    //   2585: iand
    //   2586: istore 6
    //   2588: iinc 7 1
    //   2591: iload 7
    //   2593: aload_3
    //   2594: arraylength
    //   2595: if_icmplt -76 -> 2519
    //   2598: getstatic 162	b:b	[Ljava/lang/String;
    //   2601: iload_2
    //   2602: new 55	java/lang/String
    //   2605: dup
    //   2606: aload_3
    //   2607: invokespecial 160	java/lang/String:<init>	([C)V
    //   2610: invokevirtual 153	java/lang/String:intern	()Ljava/lang/String;
    //   2613: aastore
    //   2614: getstatic 162	b:b	[Ljava/lang/String;
    //   2617: iload_2
    //   2618: aaload
    //   2619: areturn
  }
}


/* Location:              D:\COMP3331\NonObf\cdht.jar!\b.class
 * Java compiler version: 8 (52.0)
 * JD-Core Version:       0.7.1
 */