import java.io.BufferedReader;
import java.io.ByteArrayInputStream;
import java.io.InputStreamReader;
import java.net.DatagramPacket;
import java.net.DatagramSocket;

class c
  extends Thread
{
  DatagramSocket a;
  public static boolean b;
  private static final String[] c;
  private static final String[] d;
  
  public c(DatagramSocket paramDatagramSocket)
  {
    this.a = paramDatagramSocket;
  }
  
  /* Error */
  public void run()
  {
    // Byte code:
    //   0: getstatic 164	c:b	Z
    //   3: sipush 1024
    //   6: newarray <illegal type>
    //   8: astore_2
    //   9: istore_1
    //   10: new 10	java/net/DatagramPacket
    //   13: dup
    //   14: aload_2
    //   15: aload_2
    //   16: arraylength
    //   17: invokespecial 11	java/net/DatagramPacket:<init>	([BI)V
    //   20: astore_3
    //   21: aload_0
    //   22: getfield 9	c:a	Ljava/net/DatagramSocket;
    //   25: aload_3
    //   26: invokevirtual 12	java/net/DatagramSocket:receive	(Ljava/net/DatagramPacket;)V
    //   29: aload_3
    //   30: invokevirtual 13	java/net/DatagramPacket:getPort	()I
    //   33: istore 4
    //   35: aload_0
    //   36: aload_3
    //   37: invokespecial 14	c:a	(Ljava/net/DatagramPacket;)Ljava/lang/String;
    //   40: ldc 1
    //   42: invokevirtual 15	java/lang/String:split	(Ljava/lang/String;)[Ljava/lang/String;
    //   45: astore 5
    //   47: aload 5
    //   49: iconst_0
    //   50: aaload
    //   51: sipush 52614
    //   54: sipush 47562
    //   57: invokestatic 182	c:a	(II)Ljava/lang/String;
    //   60: invokevirtual 16	java/lang/String:equals	(Ljava/lang/Object;)Z
    //   63: ifeq +99 -> 162
    //   66: getstatic 17	java/lang/System:out	Ljava/io/PrintStream;
    //   69: new 18	java/lang/StringBuilder
    //   72: dup
    //   73: invokespecial 19	java/lang/StringBuilder:<init>	()V
    //   76: sipush 52615
    //   79: sipush 11621
    //   82: invokestatic 182	c:a	(II)Ljava/lang/String;
    //   85: invokevirtual 20	java/lang/StringBuilder:append	(Ljava/lang/String;)Ljava/lang/StringBuilder;
    //   88: iload 4
    //   90: ldc 2
    //   92: isub
    //   93: invokevirtual 21	java/lang/StringBuilder:append	(I)Ljava/lang/StringBuilder;
    //   96: ldc 3
    //   98: invokevirtual 20	java/lang/StringBuilder:append	(Ljava/lang/String;)Ljava/lang/StringBuilder;
    //   101: invokevirtual 22	java/lang/StringBuilder:toString	()Ljava/lang/String;
    //   104: invokevirtual 23	java/io/PrintStream:println	(Ljava/lang/String;)V
    //   107: iload 4
    //   109: ldc 2
    //   111: isub
    //   112: iload_1
    //   113: ifne +65 -> 178
    //   116: goto +4 -> 120
    //   119: athrow
    //   120: getstatic 24	a:b	I
    //   123: if_icmpne +25 -> 148
    //   126: goto +4 -> 130
    //   129: athrow
    //   130: aload 5
    //   132: iconst_1
    //   133: aaload
    //   134: invokestatic 25	java/lang/Integer:parseInt	(Ljava/lang/String;)I
    //   137: putstatic 26	a:g	I
    //   140: iload_1
    //   141: ifeq +21 -> 162
    //   144: goto +4 -> 148
    //   147: athrow
    //   148: aload 5
    //   150: iconst_1
    //   151: aaload
    //   152: invokestatic 25	java/lang/Integer:parseInt	(Ljava/lang/String;)I
    //   155: putstatic 27	a:h	I
    //   158: goto +4 -> 162
    //   161: athrow
    //   162: aload 5
    //   164: iconst_0
    //   165: aaload
    //   166: sipush 52612
    //   169: sipush 61552
    //   172: invokestatic 182	c:a	(II)Ljava/lang/String;
    //   175: invokevirtual 16	java/lang/String:equals	(Ljava/lang/Object;)Z
    //   178: ifeq +121 -> 299
    //   181: getstatic 17	java/lang/System:out	Ljava/io/PrintStream;
    //   184: new 18	java/lang/StringBuilder
    //   187: dup
    //   188: invokespecial 19	java/lang/StringBuilder:<init>	()V
    //   191: sipush 52613
    //   194: sipush 18988
    //   197: invokestatic 182	c:a	(II)Ljava/lang/String;
    //   200: invokevirtual 20	java/lang/StringBuilder:append	(Ljava/lang/String;)Ljava/lang/StringBuilder;
    //   203: iload 4
    //   205: ldc 2
    //   207: isub
    //   208: invokevirtual 21	java/lang/StringBuilder:append	(I)Ljava/lang/StringBuilder;
    //   211: ldc 3
    //   213: invokevirtual 20	java/lang/StringBuilder:append	(Ljava/lang/String;)Ljava/lang/StringBuilder;
    //   216: invokevirtual 22	java/lang/StringBuilder:toString	()Ljava/lang/String;
    //   219: invokevirtual 23	java/io/PrintStream:println	(Ljava/lang/String;)V
    //   222: aload_0
    //   223: iload 4
    //   225: ldc 2
    //   227: isub
    //   228: invokespecial 28	c:a	(I)V
    //   231: new 18	java/lang/StringBuilder
    //   234: dup
    //   235: invokespecial 19	java/lang/StringBuilder:<init>	()V
    //   238: sipush 52609
    //   241: sipush 64604
    //   244: invokestatic 182	c:a	(II)Ljava/lang/String;
    //   247: invokevirtual 20	java/lang/StringBuilder:append	(Ljava/lang/String;)Ljava/lang/StringBuilder;
    //   250: aload 5
    //   252: iconst_1
    //   253: aaload
    //   254: invokevirtual 20	java/lang/StringBuilder:append	(Ljava/lang/String;)Ljava/lang/StringBuilder;
    //   257: ldc 4
    //   259: invokevirtual 20	java/lang/StringBuilder:append	(Ljava/lang/String;)Ljava/lang/StringBuilder;
    //   262: invokevirtual 22	java/lang/StringBuilder:toString	()Ljava/lang/String;
    //   265: invokevirtual 29	java/lang/String:getBytes	()[B
    //   268: astore 6
    //   270: new 10	java/net/DatagramPacket
    //   273: dup
    //   274: aload 6
    //   276: aload 6
    //   278: arraylength
    //   279: aload_3
    //   280: invokevirtual 30	java/net/DatagramPacket:getAddress	()Ljava/net/InetAddress;
    //   283: iload 4
    //   285: invokespecial 31	java/net/DatagramPacket:<init>	([BILjava/net/InetAddress;I)V
    //   288: astore 7
    //   290: aload_0
    //   291: getfield 9	c:a	Ljava/net/DatagramSocket;
    //   294: aload 7
    //   296: invokevirtual 32	java/net/DatagramSocket:send	(Ljava/net/DatagramPacket;)V
    //   299: goto +26 -> 325
    //   302: astore 4
    //   304: getstatic 34	java/lang/System:err	Ljava/io/PrintStream;
    //   307: aload 4
    //   309: invokevirtual 35	java/io/PrintStream:println	(Ljava/lang/Object;)V
    //   312: goto +13 -> 325
    //   315: astore 4
    //   317: getstatic 34	java/lang/System:err	Ljava/io/PrintStream;
    //   320: aload 4
    //   322: invokevirtual 35	java/io/PrintStream:println	(Ljava/lang/Object;)V
    //   325: goto -315 -> 10
    // Exception table:
    //   from	to	target	type
    //   47	116	119	java/io/IOException
    //   66	126	129	java/io/IOException
    //   120	144	147	java/io/IOException
    //   130	158	161	java/io/IOException
    //   21	299	302	java/io/IOException
    //   21	299	315	java/lang/Exception
  }
  
  private String a(DatagramPacket paramDatagramPacket)
    throws Exception
  {
    byte[] arrayOfByte = paramDatagramPacket.getData();
    ByteArrayInputStream localByteArrayInputStream = new ByteArrayInputStream(arrayOfByte);
    InputStreamReader localInputStreamReader = new InputStreamReader(localByteArrayInputStream);
    BufferedReader localBufferedReader = new BufferedReader(localInputStreamReader);
    return localBufferedReader.readLine();
  }
  
  private void a(int paramInt)
  {
    boolean bool = b;
    if ((a.d == 0) && (a.e == 0))
    {
      a.d = paramInt;
      return;
    }
    if ((a.e == 0) && (a.d != 0))
    {
      if ((a.a - a.d + 256) % 256 < (a.a - paramInt + 256) % 256)
      {
        a.e = paramInt;
        if (!bool) {}
      }
      else
      {
        a.e = a.d;
        a.d = paramInt;
      }
      return;
    }
    if ((paramInt != a.d) && (paramInt != a.e))
    {
      a.d = paramInt;
      a.e = 0;
    }
  }
  
  /* Error */
  private static String a(int arg0, int arg1)
  {
    // Byte code:
    //   0: iload_0
    //   1: sipush 52613
    //   4: ixor
    //   5: ldc 5
    //   7: iand
    //   8: istore_2
    //   9: getstatic 179	c:d	[Ljava/lang/String;
    //   12: iload_2
    //   13: aaload
    //   14: ifnonnull +2600 -> 2614
    //   17: getstatic 167	c:c	[Ljava/lang/String;
    //   20: iload_2
    //   21: aaload
    //   22: invokevirtual 174	java/lang/String:toCharArray	()[C
    //   25: astore_3
    //   26: aload_3
    //   27: iconst_0
    //   28: caload
    //   29: sipush 255
    //   32: iand
    //   33: tableswitch	default:+2432->2465, 0:+1035->1068, 1:+1040->1073, 2:+1046->1079, 3:+1051->1084, 4:+1056->1089, 5:+1062->1095, 6:+1067->1100, 7:+1073->1106, 8:+1078->1111, 9:+1084->1117, 10:+1090->1123, 11:+1096->1129, 12:+1102->1135, 13:+1107->1140, 14:+1113->1146, 15:+1118->1151, 16:+1124->1157, 17:+1128->1161, 18:+1133->1166, 19:+1138->1171, 20:+1143->1176, 21:+1149->1182, 22:+1154->1187, 23:+1159->1192, 24:+1165->1198, 25:+1171->1204, 26:+1176->1209, 27:+1182->1215, 28:+1188->1221, 29:+1194->1227, 30:+1199->1232, 31:+1204->1237, 32:+1210->1243, 33:+1216->1249, 34:+1222->1255, 35:+1227->1260, 36:+1233->1266, 37:+1239->1272, 38:+1244->1277, 39:+1250->1283, 40:+1255->1288, 41:+1260->1293, 42:+1265->1298, 43:+1271->1304, 44:+1277->1310, 45:+1282->1315, 46:+1287->1320, 47:+1292->1325, 48:+1298->1331, 49:+1304->1337, 50:+1309->1342, 51:+1314->1347, 52:+1320->1353, 53:+1325->1358, 54:+1330->1363, 55:+1336->1369, 56:+1342->1375, 57:+1348->1381, 58:+1353->1386, 59:+1359->1392, 60:+1364->1397, 61:+1370->1403, 62:+1376->1409, 63:+1381->1414, 64:+1387->1420, 65:+1393->1426, 66:+1398->1431, 67:+1404->1437, 68:+1409->1442, 69:+1414->1447, 70:+1419->1452, 71:+1425->1458, 72:+1430->1463, 73:+1435->1468, 74:+1441->1474, 75:+1447->1480, 76:+1452->1485, 77:+1457->1490, 78:+1462->1495, 79:+1467->1500, 80:+1473->1506, 81:+1478->1511, 82:+1482->1515, 83:+1488->1521, 84:+1494->1527, 85:+1500->1533, 86:+1506->1539, 87:+1511->1544, 88:+1516->1549, 89:+1522->1555, 90:+1528->1561, 91:+1534->1567, 92:+1540->1573, 93:+1545->1578, 94:+1551->1584, 95:+1557->1590, 96:+1561->1594, 97:+1566->1599, 98:+1571->1604, 99:+1576->1609, 100:+1581->1614, 101:+1587->1620, 102:+1593->1626, 103:+1598->1631, 104:+1604->1637, 105:+1610->1643, 106:+1616->1649, 107:+1621->1654, 108:+1625->1658, 109:+1631->1664, 110:+1637->1670, 111:+1643->1676, 112:+1649->1682, 113:+1654->1687, 114:+1660->1693, 115:+1665->1698, 116:+1671->1704, 117:+1676->1709, 118:+1681->1714, 119:+1686->1719, 120:+1692->1725, 121:+1697->1730, 122:+1703->1736, 123:+1709->1742, 124:+1715->1748, 125:+1720->1753, 126:+1726->1759, 127:+1731->1764, 128:+1737->1770, 129:+1742->1775, 130:+1748->1781, 131:+1754->1787, 132:+1760->1793, 133:+1765->1798, 134:+1770->1803, 135:+1776->1809, 136:+1782->1815, 137:+1788->1821, 138:+1794->1827, 139:+1799->1832, 140:+1804->1837, 141:+1809->1842, 142:+1814->1847, 143:+1820->1853, 144:+1826->1859, 145:+1830->1863, 146:+1835->1868, 147:+1841->1874, 148:+1846->1879, 149:+1852->1885, 150:+1858->1891, 151:+1864->1897, 152:+1869->1902, 153:+1874->1907, 154:+1880->1913, 155:+1885->1918, 156:+1890->1923, 157:+1896->1929, 158:+1902->1935, 159:+1907->1940, 160:+1912->1945, 161:+1917->1950, 162:+1922->1955, 163:+1928->1961, 164:+1934->1967, 165:+1939->1972, 166:+1944->1977, 167:+1949->1982, 168:+1954->1987, 169:+1960->1993, 170:+1966->1999, 171:+1972->2005, 172:+1977->2010, 173:+1983->2016, 174:+1988->2021, 175:+1994->2027, 176:+1999->2032, 177:+2005->2038, 178:+2010->2043, 179:+2016->2049, 180:+2021->2054, 181:+2027->2060, 182:+2032->2065, 183:+2037->2070, 184:+2042->2075, 185:+2048->2081, 186:+2053->2086, 187:+2058->2091, 188:+2064->2097, 189:+2070->2103, 190:+2075->2108, 191:+2081->2114, 192:+2086->2119, 193:+2092->2125, 194:+2097->2130, 195:+2103->2136, 196:+2108->2141, 197:+2114->2147, 198:+2119->2152, 199:+2124->2157, 200:+2130->2163, 201:+2135->2168, 202:+2141->2174, 203:+2146->2179, 204:+2151->2184, 205:+2157->2190, 206:+2163->2196, 207:+2168->2201, 208:+2174->2207, 209:+2179->2212, 210:+2184->2217, 211:+2189->2222, 212:+2195->2228, 213:+2199->2232, 214:+2205->2238, 215:+2210->2243, 216:+2216->2249, 217:+2222->2255, 218:+2227->2260, 219:+2233->2266, 220:+2239->2272, 221:+2244->2277, 222:+2249->2282, 223:+2255->2288, 224:+2261->2294, 225:+2267->2300, 226:+2273->2306, 227:+2278->2311, 228:+2283->2316, 229:+2288->2321, 230:+2294->2327, 231:+2299->2332, 232:+2304->2337, 233:+2310->2343, 234:+2316->2349, 235:+2321->2354, 236:+2326->2359, 237:+2332->2365, 238:+2337->2370, 239:+2343->2376, 240:+2349->2382, 241:+2354->2387, 242:+2359->2392, 243:+2364->2397, 244:+2370->2403, 245:+2376->2409, 246:+2381->2414, 247:+2387->2420, 248:+2392->2425, 249:+2398->2431, 250:+2403->2436, 251:+2409->2442, 252:+2415->2448, 253:+2420->2453, 254:+2426->2459
    //   1068: bipush 78
    //   1070: goto +1397 -> 2467
    //   1073: sipush 202
    //   1076: goto +1391 -> 2467
    //   1079: bipush 104
    //   1081: goto +1386 -> 2467
    //   1084: bipush 37
    //   1086: goto +1381 -> 2467
    //   1089: sipush 231
    //   1092: goto +1375 -> 2467
    //   1095: bipush 39
    //   1097: goto +1370 -> 2467
    //   1100: sipush 169
    //   1103: goto +1364 -> 2467
    //   1106: bipush 65
    //   1108: goto +1359 -> 2467
    //   1111: sipush 241
    //   1114: goto +1353 -> 2467
    //   1117: sipush 223
    //   1120: goto +1347 -> 2467
    //   1123: sipush 156
    //   1126: goto +1341 -> 2467
    //   1129: sipush 228
    //   1132: goto +1335 -> 2467
    //   1135: bipush 35
    //   1137: goto +1330 -> 2467
    //   1140: sipush 245
    //   1143: goto +1324 -> 2467
    //   1146: bipush 58
    //   1148: goto +1319 -> 2467
    //   1151: sipush 216
    //   1154: goto +1313 -> 2467
    //   1157: iconst_0
    //   1158: goto +1309 -> 2467
    //   1161: bipush 89
    //   1163: goto +1304 -> 2467
    //   1166: bipush 75
    //   1168: goto +1299 -> 2467
    //   1171: bipush 92
    //   1173: goto +1294 -> 2467
    //   1176: sipush 220
    //   1179: goto +1288 -> 2467
    //   1182: bipush 47
    //   1184: goto +1283 -> 2467
    //   1187: bipush 105
    //   1189: goto +1278 -> 2467
    //   1192: sipush 133
    //   1195: goto +1272 -> 2467
    //   1198: sipush 239
    //   1201: goto +1266 -> 2467
    //   1204: bipush 126
    //   1206: goto +1261 -> 2467
    //   1209: sipush 217
    //   1212: goto +1255 -> 2467
    //   1215: sipush 162
    //   1218: goto +1249 -> 2467
    //   1221: sipush 227
    //   1224: goto +1243 -> 2467
    //   1227: bipush 44
    //   1229: goto +1238 -> 2467
    //   1232: bipush 33
    //   1234: goto +1233 -> 2467
    //   1237: sipush 190
    //   1240: goto +1227 -> 2467
    //   1243: sipush 159
    //   1246: goto +1221 -> 2467
    //   1249: sipush 247
    //   1252: goto +1215 -> 2467
    //   1255: bipush 107
    //   1257: goto +1210 -> 2467
    //   1260: sipush 205
    //   1263: goto +1204 -> 2467
    //   1266: sipush 157
    //   1269: goto +1198 -> 2467
    //   1272: bipush 70
    //   1274: goto +1193 -> 2467
    //   1277: sipush 146
    //   1280: goto +1187 -> 2467
    //   1283: bipush 62
    //   1285: goto +1182 -> 2467
    //   1288: bipush 109
    //   1290: goto +1177 -> 2467
    //   1293: bipush 83
    //   1295: goto +1172 -> 2467
    //   1298: sipush 249
    //   1301: goto +1166 -> 2467
    //   1304: sipush 197
    //   1307: goto +1160 -> 2467
    //   1310: bipush 28
    //   1312: goto +1155 -> 2467
    //   1315: bipush 6
    //   1317: goto +1150 -> 2467
    //   1320: bipush 117
    //   1322: goto +1145 -> 2467
    //   1325: sipush 221
    //   1328: goto +1139 -> 2467
    //   1331: sipush 149
    //   1334: goto +1133 -> 2467
    //   1337: bipush 106
    //   1339: goto +1128 -> 2467
    //   1342: bipush 17
    //   1344: goto +1123 -> 2467
    //   1347: sipush 189
    //   1350: goto +1117 -> 2467
    //   1353: bipush 43
    //   1355: goto +1112 -> 2467
    //   1358: bipush 56
    //   1360: goto +1107 -> 2467
    //   1363: sipush 163
    //   1366: goto +1101 -> 2467
    //   1369: sipush 180
    //   1372: goto +1095 -> 2467
    //   1375: sipush 233
    //   1378: goto +1089 -> 2467
    //   1381: bipush 125
    //   1383: goto +1084 -> 2467
    //   1386: sipush 242
    //   1389: goto +1078 -> 2467
    //   1392: bipush 97
    //   1394: goto +1073 -> 2467
    //   1397: sipush 137
    //   1400: goto +1067 -> 2467
    //   1403: sipush 200
    //   1406: goto +1061 -> 2467
    //   1409: bipush 113
    //   1411: goto +1056 -> 2467
    //   1414: sipush 176
    //   1417: goto +1050 -> 2467
    //   1420: sipush 252
    //   1423: goto +1044 -> 2467
    //   1426: bipush 34
    //   1428: goto +1039 -> 2467
    //   1431: sipush 187
    //   1434: goto +1033 -> 2467
    //   1437: bipush 73
    //   1439: goto +1028 -> 2467
    //   1442: bipush 116
    //   1444: goto +1023 -> 2467
    //   1447: bipush 41
    //   1449: goto +1018 -> 2467
    //   1452: sipush 215
    //   1455: goto +1012 -> 2467
    //   1458: bipush 48
    //   1460: goto +1007 -> 2467
    //   1463: bipush 30
    //   1465: goto +1002 -> 2467
    //   1468: sipush 184
    //   1471: goto +996 -> 2467
    //   1474: sipush 151
    //   1477: goto +990 -> 2467
    //   1480: bipush 102
    //   1482: goto +985 -> 2467
    //   1485: bipush 57
    //   1487: goto +980 -> 2467
    //   1490: bipush 118
    //   1492: goto +975 -> 2467
    //   1495: bipush 55
    //   1497: goto +970 -> 2467
    //   1500: sipush 164
    //   1503: goto +964 -> 2467
    //   1506: bipush 69
    //   1508: goto +959 -> 2467
    //   1511: iconst_2
    //   1512: goto +955 -> 2467
    //   1515: sipush 229
    //   1518: goto +949 -> 2467
    //   1521: sipush 204
    //   1524: goto +943 -> 2467
    //   1527: sipush 213
    //   1530: goto +937 -> 2467
    //   1533: sipush 144
    //   1536: goto +931 -> 2467
    //   1539: bipush 45
    //   1541: goto +926 -> 2467
    //   1544: bipush 51
    //   1546: goto +921 -> 2467
    //   1549: sipush 170
    //   1552: goto +915 -> 2467
    //   1555: sipush 128
    //   1558: goto +909 -> 2467
    //   1561: sipush 147
    //   1564: goto +903 -> 2467
    //   1567: sipush 182
    //   1570: goto +897 -> 2467
    //   1573: bipush 111
    //   1575: goto +892 -> 2467
    //   1578: sipush 165
    //   1581: goto +886 -> 2467
    //   1584: sipush 136
    //   1587: goto +880 -> 2467
    //   1590: iconst_5
    //   1591: goto +876 -> 2467
    //   1594: bipush 90
    //   1596: goto +871 -> 2467
    //   1599: bipush 26
    //   1601: goto +866 -> 2467
    //   1604: bipush 68
    //   1606: goto +861 -> 2467
    //   1609: bipush 23
    //   1611: goto +856 -> 2467
    //   1614: sipush 232
    //   1617: goto +850 -> 2467
    //   1620: sipush 175
    //   1623: goto +844 -> 2467
    //   1626: bipush 115
    //   1628: goto +839 -> 2467
    //   1631: sipush 166
    //   1634: goto +833 -> 2467
    //   1637: sipush 143
    //   1640: goto +827 -> 2467
    //   1643: sipush 208
    //   1646: goto +821 -> 2467
    //   1649: bipush 13
    //   1651: goto +816 -> 2467
    //   1654: iconst_3
    //   1655: goto +812 -> 2467
    //   1658: sipush 171
    //   1661: goto +806 -> 2467
    //   1664: sipush 195
    //   1667: goto +800 -> 2467
    //   1670: sipush 188
    //   1673: goto +794 -> 2467
    //   1676: sipush 218
    //   1679: goto +788 -> 2467
    //   1682: bipush 25
    //   1684: goto +783 -> 2467
    //   1687: sipush 131
    //   1690: goto +777 -> 2467
    //   1693: bipush 101
    //   1695: goto +772 -> 2467
    //   1698: sipush 237
    //   1701: goto +766 -> 2467
    //   1704: bipush 40
    //   1706: goto +761 -> 2467
    //   1709: bipush 112
    //   1711: goto +756 -> 2467
    //   1714: bipush 67
    //   1716: goto +751 -> 2467
    //   1719: sipush 174
    //   1722: goto +745 -> 2467
    //   1725: bipush 11
    //   1727: goto +740 -> 2467
    //   1730: sipush 199
    //   1733: goto +734 -> 2467
    //   1736: sipush 196
    //   1739: goto +728 -> 2467
    //   1742: sipush 186
    //   1745: goto +722 -> 2467
    //   1748: bipush 80
    //   1750: goto +717 -> 2467
    //   1753: sipush 178
    //   1756: goto +711 -> 2467
    //   1759: bipush 38
    //   1761: goto +706 -> 2467
    //   1764: sipush 129
    //   1767: goto +700 -> 2467
    //   1770: bipush 10
    //   1772: goto +695 -> 2467
    //   1775: sipush 183
    //   1778: goto +689 -> 2467
    //   1781: sipush 243
    //   1784: goto +683 -> 2467
    //   1787: sipush 148
    //   1790: goto +677 -> 2467
    //   1793: bipush 16
    //   1795: goto +672 -> 2467
    //   1798: bipush 85
    //   1800: goto +667 -> 2467
    //   1803: sipush 185
    //   1806: goto +661 -> 2467
    //   1809: sipush 135
    //   1812: goto +655 -> 2467
    //   1815: sipush 235
    //   1818: goto +649 -> 2467
    //   1821: sipush 139
    //   1824: goto +643 -> 2467
    //   1827: bipush 64
    //   1829: goto +638 -> 2467
    //   1832: bipush 46
    //   1834: goto +633 -> 2467
    //   1837: bipush 24
    //   1839: goto +628 -> 2467
    //   1842: bipush 42
    //   1844: goto +623 -> 2467
    //   1847: sipush 234
    //   1850: goto +617 -> 2467
    //   1853: sipush 244
    //   1856: goto +611 -> 2467
    //   1859: iconst_1
    //   1860: goto +607 -> 2467
    //   1863: bipush 110
    //   1865: goto +602 -> 2467
    //   1868: sipush 179
    //   1871: goto +596 -> 2467
    //   1874: bipush 36
    //   1876: goto +591 -> 2467
    //   1879: sipush 224
    //   1882: goto +585 -> 2467
    //   1885: sipush 154
    //   1888: goto +579 -> 2467
    //   1891: sipush 240
    //   1894: goto +573 -> 2467
    //   1897: bipush 120
    //   1899: goto +568 -> 2467
    //   1902: bipush 52
    //   1904: goto +563 -> 2467
    //   1907: sipush 140
    //   1910: goto +557 -> 2467
    //   1913: bipush 15
    //   1915: goto +552 -> 2467
    //   1918: bipush 86
    //   1920: goto +547 -> 2467
    //   1923: sipush 142
    //   1926: goto +541 -> 2467
    //   1929: sipush 132
    //   1932: goto +535 -> 2467
    //   1935: bipush 103
    //   1937: goto +530 -> 2467
    //   1940: bipush 14
    //   1942: goto +525 -> 2467
    //   1945: bipush 93
    //   1947: goto +520 -> 2467
    //   1950: bipush 87
    //   1952: goto +515 -> 2467
    //   1955: sipush 253
    //   1958: goto +509 -> 2467
    //   1961: sipush 155
    //   1964: goto +503 -> 2467
    //   1967: bipush 79
    //   1969: goto +498 -> 2467
    //   1972: bipush 18
    //   1974: goto +493 -> 2467
    //   1977: bipush 59
    //   1979: goto +488 -> 2467
    //   1982: bipush 50
    //   1984: goto +483 -> 2467
    //   1987: sipush 168
    //   1990: goto +477 -> 2467
    //   1993: sipush 222
    //   1996: goto +471 -> 2467
    //   1999: sipush 198
    //   2002: goto +465 -> 2467
    //   2005: bipush 71
    //   2007: goto +460 -> 2467
    //   2010: sipush 230
    //   2013: goto +454 -> 2467
    //   2016: bipush 94
    //   2018: goto +449 -> 2467
    //   2021: sipush 181
    //   2024: goto +443 -> 2467
    //   2027: bipush 91
    //   2029: goto +438 -> 2467
    //   2032: sipush 251
    //   2035: goto +432 -> 2467
    //   2038: bipush 84
    //   2040: goto +427 -> 2467
    //   2043: sipush 192
    //   2046: goto +421 -> 2467
    //   2049: bipush 123
    //   2051: goto +416 -> 2467
    //   2054: sipush 206
    //   2057: goto +410 -> 2467
    //   2060: bipush 96
    //   2062: goto +405 -> 2467
    //   2065: bipush 53
    //   2067: goto +400 -> 2467
    //   2070: bipush 114
    //   2072: goto +395 -> 2467
    //   2075: sipush 210
    //   2078: goto +389 -> 2467
    //   2081: bipush 74
    //   2083: goto +384 -> 2467
    //   2086: bipush 20
    //   2088: goto +379 -> 2467
    //   2091: sipush 153
    //   2094: goto +373 -> 2467
    //   2097: sipush 226
    //   2100: goto +367 -> 2467
    //   2103: bipush 119
    //   2105: goto +362 -> 2467
    //   2108: sipush 134
    //   2111: goto +356 -> 2467
    //   2114: bipush 100
    //   2116: goto +351 -> 2467
    //   2119: sipush 161
    //   2122: goto +345 -> 2467
    //   2125: bipush 72
    //   2127: goto +340 -> 2467
    //   2130: sipush 158
    //   2133: goto +334 -> 2467
    //   2136: bipush 54
    //   2138: goto +329 -> 2467
    //   2141: sipush 212
    //   2144: goto +323 -> 2467
    //   2147: bipush 49
    //   2149: goto +318 -> 2467
    //   2152: bipush 27
    //   2154: goto +313 -> 2467
    //   2157: sipush 238
    //   2160: goto +307 -> 2467
    //   2163: bipush 7
    //   2165: goto +302 -> 2467
    //   2168: sipush 203
    //   2171: goto +296 -> 2467
    //   2174: bipush 98
    //   2176: goto +291 -> 2467
    //   2179: bipush 127
    //   2181: goto +286 -> 2467
    //   2184: sipush 211
    //   2187: goto +280 -> 2467
    //   2190: sipush 172
    //   2193: goto +274 -> 2467
    //   2196: bipush 9
    //   2198: goto +269 -> 2467
    //   2201: sipush 236
    //   2204: goto +263 -> 2467
    //   2207: bipush 99
    //   2209: goto +258 -> 2467
    //   2212: bipush 76
    //   2214: goto +253 -> 2467
    //   2217: bipush 82
    //   2219: goto +248 -> 2467
    //   2222: sipush 150
    //   2225: goto +242 -> 2467
    //   2228: iconst_4
    //   2229: goto +238 -> 2467
    //   2232: sipush 250
    //   2235: goto +232 -> 2467
    //   2238: bipush 19
    //   2240: goto +227 -> 2467
    //   2243: sipush 141
    //   2246: goto +221 -> 2467
    //   2249: sipush 173
    //   2252: goto +215 -> 2467
    //   2255: bipush 31
    //   2257: goto +210 -> 2467
    //   2260: sipush 201
    //   2263: goto +204 -> 2467
    //   2266: sipush 167
    //   2269: goto +198 -> 2467
    //   2272: bipush 88
    //   2274: goto +193 -> 2467
    //   2277: bipush 29
    //   2279: goto +188 -> 2467
    //   2282: sipush 248
    //   2285: goto +182 -> 2467
    //   2288: sipush 225
    //   2291: goto +176 -> 2467
    //   2294: sipush 209
    //   2297: goto +170 -> 2467
    //   2300: sipush 246
    //   2303: goto +164 -> 2467
    //   2306: bipush 81
    //   2308: goto +159 -> 2467
    //   2311: bipush 66
    //   2313: goto +154 -> 2467
    //   2316: bipush 77
    //   2318: goto +149 -> 2467
    //   2321: sipush 138
    //   2324: goto +143 -> 2467
    //   2327: bipush 22
    //   2329: goto +138 -> 2467
    //   2332: bipush 60
    //   2334: goto +133 -> 2467
    //   2337: sipush 152
    //   2340: goto +127 -> 2467
    //   2343: sipush 194
    //   2346: goto +121 -> 2467
    //   2349: bipush 8
    //   2351: goto +116 -> 2467
    //   2354: bipush 12
    //   2356: goto +111 -> 2467
    //   2359: sipush 130
    //   2362: goto +105 -> 2467
    //   2365: bipush 63
    //   2367: goto +100 -> 2467
    //   2370: sipush 191
    //   2373: goto +94 -> 2467
    //   2376: sipush 160
    //   2379: goto +88 -> 2467
    //   2382: bipush 32
    //   2384: goto +83 -> 2467
    //   2387: bipush 21
    //   2389: goto +78 -> 2467
    //   2392: bipush 95
    //   2394: goto +73 -> 2467
    //   2397: sipush 145
    //   2400: goto +67 -> 2467
    //   2403: sipush 207
    //   2406: goto +61 -> 2467
    //   2409: bipush 108
    //   2411: goto +56 -> 2467
    //   2414: sipush 193
    //   2417: goto +50 -> 2467
    //   2420: bipush 122
    //   2422: goto +45 -> 2467
    //   2425: sipush 177
    //   2428: goto +39 -> 2467
    //   2431: bipush 124
    //   2433: goto +34 -> 2467
    //   2436: sipush 255
    //   2439: goto +28 -> 2467
    //   2442: sipush 219
    //   2445: goto +22 -> 2467
    //   2448: bipush 61
    //   2450: goto +17 -> 2467
    //   2453: sipush 214
    //   2456: goto +11 -> 2467
    //   2459: sipush 254
    //   2462: goto +5 -> 2467
    //   2465: bipush 121
    //   2467: istore 4
    //   2469: iload_1
    //   2470: sipush 255
    //   2473: iand
    //   2474: iload 4
    //   2476: isub
    //   2477: istore 5
    //   2479: iload 5
    //   2481: ifge +9 -> 2490
    //   2484: wide
    //   2490: iload_1
    //   2491: ldc 5
    //   2493: iand
    //   2494: bipush 8
    //   2496: iushr
    //   2497: iload 4
    //   2499: isub
    //   2500: istore 6
    //   2502: iload 6
    //   2504: ifge +9 -> 2513
    //   2507: wide
    //   2513: iconst_0
    //   2514: istore 7
    //   2516: goto +75 -> 2591
    //   2519: iload 7
    //   2521: iconst_2
    //   2522: irem
    //   2523: istore 8
    //   2525: aload_3
    //   2526: iload 7
    //   2528: dup2
    //   2529: caload
    //   2530: iload 8
    //   2532: ifne +31 -> 2563
    //   2535: iload 5
    //   2537: ixor
    //   2538: i2c
    //   2539: castore
    //   2540: iload 5
    //   2542: iconst_3
    //   2543: iushr
    //   2544: iload 5
    //   2546: iconst_5
    //   2547: ishl
    //   2548: ior
    //   2549: aload_3
    //   2550: iload 7
    //   2552: caload
    //   2553: ixor
    //   2554: sipush 255
    //   2557: iand
    //   2558: istore 5
    //   2560: goto +28 -> 2588
    //   2563: iload 6
    //   2565: ixor
    //   2566: i2c
    //   2567: castore
    //   2568: iload 6
    //   2570: iconst_3
    //   2571: iushr
    //   2572: iload 6
    //   2574: iconst_5
    //   2575: ishl
    //   2576: ior
    //   2577: aload_3
    //   2578: iload 7
    //   2580: caload
    //   2581: ixor
    //   2582: sipush 255
    //   2585: iand
    //   2586: istore 6
    //   2588: iinc 7 1
    //   2591: iload 7
    //   2593: aload_3
    //   2594: arraylength
    //   2595: if_icmplt -76 -> 2519
    //   2598: getstatic 179	c:d	[Ljava/lang/String;
    //   2601: iload_2
    //   2602: new 78	java/lang/String
    //   2605: dup
    //   2606: aload_3
    //   2607: invokespecial 177	java/lang/String:<init>	([C)V
    //   2610: invokevirtual 170	java/lang/String:intern	()Ljava/lang/String;
    //   2613: aastore
    //   2614: getstatic 179	c:d	[Ljava/lang/String;
    //   2617: iload_2
    //   2618: aaload
    //   2619: areturn
  }
}


/* Location:              D:\COMP3331\NonObf\cdht.jar!\c.class
 * Java compiler version: 8 (52.0)
 * JD-Core Version:       0.7.1
 */